[
  {
    "source_url": "https://advaitasharada.sringeri.net/display/bhashya/BS/devanagari",
    "source_sha256": "3e25449a44a0e912318db91030eb2e604e0c4eb2f8b5ceaa4ff4f92ae5e5bb80",
    "chapter_id": "BS_C01",
    "section_id": "BS_C01_S02",
    "verse_id": "BS_C01_S02_V01",
    "block_id": "BS_C01_S02_V01_B1",
    "block_type": "bhashya",
    "text": "इद मा म्नायते — ‘ सर्वं खल्विदं ब्रह्म तज्जलानिति शान्त उपासीत । अथ खलु क्रतुमयः पुरुषो यथा क्रतुरस्मिँल्लोके पुरुषो भवति तथेतः प्रेत्य भवति स क्रतुं कुर्वीत ’ (छा. उ. ३ । १४ । १) , ‘ मनो मयः प्राणशरीरः ’ (छा. उ. ३ । १४ । २) इत्यादि । तत्र संशयः — किमिह मनोमयत्वादिभिर्धर्मैः शारीर आत्मोपास्यत्वेनोपदिश्यते , आहोस्वित्परं ब्रह्मेति । किं तावत्प्राप्तम् ? शारीर इति । कुतः ? तस्य हि कार्यकरणाधिपतेः प्रसिद्धो मनआदिभिः सम्बन्धः , न परस्य ब्रह्मणः ; ‘ अप्राणो ह्यमनाः शुभ्रः ’ (मु. उ. २ । १ । २) इत्यादिश्रुतिभ्यः । ननु ‘ सर्वं खल्विदं ब्रह्म ’ इति स्वशब्देनैव ब्रह्मोपात्तम् ; कथमिह शारीर आत्मोपास्यत्वेनाशङ्क्यते ? नैष दोषः । नेदं वाक्यं ब्रह्मोपासनाविधिपरम् । किं तर्हि ? शमविधिपरम् ; यत्कारणम् ‘ सर्वं खल्विदं ब्रह्म तज्जलानिति शान्त उपासीत ’ इत्याह । एतदुक्तं भवति — यस्मात्सर्वमिदं विकारजातं ब्रह्मैव , तज्जत्वात् तल्लत्वात् तदनत्वाच्च — न च सर्वस्यैकात्मत्वे रागादयः सम्भवन्ति — तस्मात् शान्त उपासीतेति । न च शम विधिपरत्वे सत्यनेन वाक्येन ब्रह्मोपासनं नियन्तुं शक्यते । उपासनं तु ‘ स क्रतुं कुर्वीत ’ इत्यनेन विधीयते । क्रतुः सङ्कल्पो ध्यानमित्यर्थः । तस्य च विषयत्वेन श्रूयते — ‘ मनोमयः प्राणशरीरः ’ इति जीवलिङ्गम् । अतो ब्रूमः — जीवविषयमेतदुपासनमिति । ‘ सर्वकर्मा सर्वकामः ’ इत्याद्यपि श्रूयमाणं पर्यायेण जीवविषयमुपपद्यते । ‘ एष म आत्मान्तर्हृदयेऽणीयान्व्रीहेर्वा यवाद्वा ’ इति च हृदयायतनत्वमणीयस्त्वं चा राग्रमात्रस्य जीवस्यावकल्पते , नापरिच्छिन्नस्य ब्रह्मणः । ननु ‘ ज्यायान्पृथिव्याः ’ इत्याद्यपि न परिच्छिन्नेऽवकल्पत इति । अत्र ब्रूमः — न तावदणीयस्त्वं ज्यायस्त्वं चोभयमेकस्मिन्समाश्रयितुं शक्यम् , विरोधात् । अन्यतराश्रयणे च , प्रथमश्रुतत्वादणीयस्त्वं युक्तमाश्रयितुम् । ज्यायस्त्वं तु ब्रह्मभावापेक्षया भविष्यतीति । निश्चिते च जीवविषयत्वे यदन्ते ब्रह्मसङ्कीर्तनम् — ‘ एतद्ब्रह्म ’ (छा. उ. ३ । १४ । ४) इति , तदपि प्रकृतपरामर्शार्थत्वाज्जीवविषयमेव । तस्मान्मनोमयत्वादिभिर्धर्मैर्जीव उपास्य इत्येवं प्राप्ते ब्रूमः —",
    "citations": [
      {
        "href": "Chandogya?id=Ch_C03_S14_V01",
        "text": "‘ सर्वं"
      },
      {
        "href": "Chandogya?id=Ch_C03_S14_V02",
        "text": "‘ मनो"
      },
      {
        "href": "Mundaka?id=MD_C02_S01_V02",
        "text": "‘ अप्राणो"
      },
      {
        "href": "Chandogya?id=Ch_C03_S14_V04",
        "text": "‘ एतद्ब्रह्म"
      }
    ]
  },
  {
    "source_url": "https://advaitasharada.sringeri.net/display/bhashya/BS/devanagari",
    "source_sha256": "3e25449a44a0e912318db91030eb2e604e0c4eb2f8b5ceaa4ff4f92ae5e5bb80",
    "chapter_id": "BS_C01",
    "section_id": "BS_C01_S02",
    "verse_id": "BS_C01_S02_V01",
    "block_id": "BS_C01_S02_V01_B2",
    "block_type": "bhashya",
    "text": "परमेव ब्रह्मेह मनोमयत्वादिभिर्धर्मैरुपास्यम् । कुतः ? सर्वत्र प्रसिद्धोपदेशात् । यत्सर्वेषु वेदान्तेषु प्रसिद्धं ब्रह्मशब्दस्यालम्बनं जगत्कारणम् , इह च ‘ सर्वं खल्विदं ब्रह्म ’ इति वाक्योपक्रमे श्रुतम् , तदेव मनोमयत्वादिधर्मैर्विशिष्टमुपदिश्यत इति युक्तम् । एवं च सति प्रकृतहानाप्रकृतप्रक्रिये न भविष्यतः । ननु वाक्योपक्रमे शमविधिविवक्षया ब्रह्म निर्दिष्टं न स्वविवक्षयेत्युक्तम् ; अत्रोच्यते — यद्यपि शमविधिविवक्षया ब्रह्म निर्दिष्टम् , तथापि मनोमयत्वादिषूपदिश्यमानेषु तदेव ब्रह्म सन्निहितं भवति , जीवस्तु न सन्निहितः , न च स्वशब्देनोपात्त इति वैषम्यम् ॥ १ ॥",
    "citations": []
  },
  {
    "source_url": "https://advaitasharada.sringeri.net/display/bhashya/BS/devanagari",
    "source_sha256": "3e25449a44a0e912318db91030eb2e604e0c4eb2f8b5ceaa4ff4f92ae5e5bb80",
    "chapter_id": "BS_C01",
    "section_id": "BS_C01_S02",
    "verse_id": "BS_C01_S02_V01",
    "block_id": "BS_C01_S02_V01_VERSETEXT_01",
    "block_type": "versetext",
    "text": "सर्वत्र प्रसिद्धोपदेशात् ॥ १ ॥",
    "citations": []
  },
  {
    "source_url": "https://advaitasharada.sringeri.net/display/bhashya/BS/devanagari",
    "source_sha256": "3e25449a44a0e912318db91030eb2e604e0c4eb2f8b5ceaa4ff4f92ae5e5bb80",
    "chapter_id": "BS_C01",
    "section_id": "BS_C01_S02",
    "verse_id": "BS_C01_S02_V02",
    "block_id": "BS_C01_S02_V02_B1",
    "block_type": "bhashya",
    "text": "वक्तुमिष्टा विवक्षिताः । यद्यप्यपौरुषेये वेदे वक्तुरभावात् नेच्छार्थः सम्भवति , तथाप्युपादानेन फलेनोपचर्यते । लोके हि यच्छब्दाभिहितमुपादेयं भवति तद्विवक्षितमित्युच्यते , यदनुपादेयं तदविवक्षितमिति । तद्वद्वेदेऽप्युपादेयत्वेनाभिहितं विवक्षितं भवति , इतरदविवक्षितम् । उपादानानुपादाने तु वेदवाक्यतात्पर्यातात्पर्याभ्यामवगम्येते । तदिह ये विवक्षिता गुणा उपासनायामुपादेयत्वेनोपदिष्टाः सत्यसङ्कल्पप्रभृतयः , ते परस्मिन्ब्रह्मण्युपपद्यन्ते । सत्यसङ्कल्पत्वं हि सृष्टिस्थितिसंहारेष्वप्रतिबद्धशक्तित्वात्परमात्मन एवावकल्पते । परमात्मगुणत्वेन च ‘ य आत्मापहतपाप्मा ’ (छा. उ. ८ । ७ । १) इत्यत्र ‘ सत्यकामः सत्यसङ्कल्पः ’ इति श्रुतम् , ‘ आकाशात्मा ’ इति च आकाशवदात्मा अस्येत्यर्थः । सर्वगतत्वादिभिर्धर्मैः सम्भवत्याकाशेन साम्यं ब्रह्मणः । ‘ ज्यायान्पृथिव्याः ’ इत्यादिना चैतदेव दर्शयति । यदापि आकाश आत्मा यस्येति व्याख्यायते , तदापि सम्भवति सर्वजगत्कारणस्य सर्वात्मनो ब्रह्मण आकाशात्मत्वम् । अत एव ‘ सर्वकर्मा ’ इत्यादि । एवमिहोपास्यतया विवक्षिता गुणा ब्रह्मण्युपपद्यन्ते । यत्तूक्तम् — ‘ मनोमयः प्राणशरीरः ’ इति जीवलिङ्गम् , न तद्ब्रह्मण्युपपद्यत इति ; तदपि ब्रह्मण्युपपद्यत इति ब्रूमः । सर्वात्मत्वाद्धि ब्रह्मणो जीवसम्बन्धीनि मनोमयत्वादीनि ब्रह्मसम्बन्धीनि भवन्ति । तथा च ब्रह्मविषये श्रुतिस्मृती भवतः — ‘ त्वं स्त्री त्वं पुमानसि त्वं कुमार उत वा कुमारी । त्वं जीर्णो दण्डेन वञ्चसि त्वं जातो भवसि विश्वतोमुखः ’ (श्वे. उ. ४ । ३) इति ; ‘ सर्वतःपाणिपादं तत्सर्वतोऽक्षिशिरोमुखम् । सर्वतःश्रुतिमल्लोके सर्वमावृत्य तिष्ठति ’ (भ. गी. १३ । १३) इति च । ‘ अप्राणो ह्यमनाः शुभ्रः ’ इति श्रुतिः शुद्धब्रह्मविषया , इयं तु श्रुतिः ‘ मनोमयः प्राणशरीरः ’ इति सगुणब्रह्मविषयेति विशेषः । अतो विवक्षितगुणोपपत्तेः परमेव ब्रह्म इहोपास्यत्वेनोपदिष्टमिति गम्यते ॥ २ ॥",
    "citations": [
      {
        "href": "Chandogya?id=Ch_C08_S07_V01",
        "text": "‘ य"
      },
      {
        "href": "svt?id=SV_C04_V03",
        "text": "‘ त्वं"
      },
      {
        "href": "Gita?id=BG_C13_V13",
        "text": "‘ सर्वतःपाणिपादं"
      }
    ]
  },
  {
    "source_url": "https://advaitasharada.sringeri.net/display/bhashya/BS/devanagari",
    "source_sha256": "3e25449a44a0e912318db91030eb2e604e0c4eb2f8b5ceaa4ff4f92ae5e5bb80",
    "chapter_id": "BS_C01",
    "section_id": "BS_C01_S02",
    "verse_id": "BS_C01_S02_V02",
    "block_id": "BS_C01_S02_V02_VERSETEXT_01",
    "block_type": "versetext",
    "text": "विवक्षितगुणोपपत्तेश्च ॥ २ ॥",
    "citations": []
  },
  {
    "source_url": "https://advaitasharada.sringeri.net/display/bhashya/BS/devanagari",
    "source_sha256": "3e25449a44a0e912318db91030eb2e604e0c4eb2f8b5ceaa4ff4f92ae5e5bb80",
    "chapter_id": "BS_C01",
    "section_id": "BS_C01_S02",
    "verse_id": "BS_C01_S02_V03",
    "block_id": "BS_C01_S02_V03_B1",
    "block_type": "bhashya",
    "text": "पूर्वेण सूत्रेण ब्रह्मणि विवक्षितानां गुणानामुपपत्तिरुक्ता । अनेन शारीरे तेषामनुपपत्तिरुच्यते । तुशब्दोऽवधारणार्थः । ब्रह्मैवोक्तेन न्यायेन मनोमयत्वादिगुणम् ; न तु शारीरो जीवो मनोमयत्वादिगुणः ; यत्कारणम् — ‘ सत्यसङ्कल्पः ’ ‘ आकाशात्मा ’ ‘ अवाकी ’ ‘ अनादरः ’ ‘ ज्यायान्पृथिव्याः ’ इति चैवंजातीयका गुणा न शारीरे आञ्जस्येनोपपद्यन्ते । शारीर इति शरीरे भव इत्यर्थः । नन्वीश्वरोऽपि शरीरे भवति । सत्यम् , शरीरे भवति ; न तु शरीर एव भवति ; ‘ ज्यायान्पृथिव्या ज्यायानन्तरिक्षात् ’ ‘ आकाशवत्सर्वगतश्च नित्यः ’ (शत. ब्रा. १० । ६ । ३ । २) इति च व्यापित्वश्रवणात् । जीवस्तु शरीर एव भवति , तस्य भोगाधिष्ठानाच्छरीरादन्यत्र वृत्त्यभावात् ॥ ३ ॥",
    "citations": [
      {
        "href": "",
        "text": "‘ आकाशवत्सर्वगतश्च"
      }
    ]
  },
  {
    "source_url": "https://advaitasharada.sringeri.net/display/bhashya/BS/devanagari",
    "source_sha256": "3e25449a44a0e912318db91030eb2e604e0c4eb2f8b5ceaa4ff4f92ae5e5bb80",
    "chapter_id": "BS_C01",
    "section_id": "BS_C01_S02",
    "verse_id": "BS_C01_S02_V03",
    "block_id": "BS_C01_S02_V03_VERSETEXT_01",
    "block_type": "versetext",
    "text": "अनुपपत्तेस्तु न शारीरः ॥ ३ ॥",
    "citations": []
  },
  {
    "source_url": "https://advaitasharada.sringeri.net/display/bhashya/BS/devanagari",
    "source_sha256": "3e25449a44a0e912318db91030eb2e604e0c4eb2f8b5ceaa4ff4f92ae5e5bb80",
    "chapter_id": "BS_C01",
    "section_id": "BS_C01_S02",
    "verse_id": "BS_C01_S02_V04",
    "block_id": "BS_C01_S02_V04_B1",
    "block_type": "bhashya",
    "text": "इतश्च न शारीरो मनोमयत्वादिगुणः ; यस्मात्कर्मकर्तृव्यपदेशो भवति — ‘ एतमितः प्रेत्याभिसम्भवितास्मि ’ (छा. उ. ३ । १४ । ४) इति । एतमिति प्रकृतं मनोमयत्वादिगुणमुपास्यमात्मानं कर्मत्वेन प्राप्यत्वेन व्यपदिशति ; अभिसम्भवितास्मीति शारीरमुपासकं कर्तृत्वेन प्रापकत्वेन । अभिसम्भवितास्मीति प्राप्तास्मीत्यर्थः । न च सत्यां गतावेकस्य कर्मकर्तृव्यपदेशो युक्तः । तथोपा स्यो पासकभावोऽपि भेदाधिष्ठान एव । तस्मादपि न शारीरो मनोमयत्वादिविशिष्टः ॥ ४ ॥",
    "citations": [
      {
        "href": "Chandogya?id=Ch_C03_S14_V04",
        "text": "‘ एतमितः"
      }
    ]
  },
  {
    "source_url": "https://advaitasharada.sringeri.net/display/bhashya/BS/devanagari",
    "source_sha256": "3e25449a44a0e912318db91030eb2e604e0c4eb2f8b5ceaa4ff4f92ae5e5bb80",
    "chapter_id": "BS_C01",
    "section_id": "BS_C01_S02",
    "verse_id": "BS_C01_S02_V04",
    "block_id": "BS_C01_S02_V04_VERSETEXT_01",
    "block_type": "versetext",
    "text": "कर्मकर्तृव्यपदेशाच्च ॥ ४ ॥",
    "citations": []
  },
  {
    "source_url": "https://advaitasharada.sringeri.net/display/bhashya/BS/devanagari",
    "source_sha256": "3e25449a44a0e912318db91030eb2e604e0c4eb2f8b5ceaa4ff4f92ae5e5bb80",
    "chapter_id": "BS_C01",
    "section_id": "BS_C01_S02",
    "verse_id": "BS_C01_S02_V05",
    "block_id": "BS_C01_S02_V05_B1",
    "block_type": "bhashya",
    "text": "इतश्च शारीरादन्यो मनोमयत्वादिगुणः ; यस्माच्छब्दविशेषो भवति समानप्रकरणे श्रुत्यन्तरे — ‘ यथा व्रीहिर्वा यवो वा श्यामाको वा श्यामाकतण्डुलो वैवमयमन्तरात्मन्पुरुषो हिरण्मयः ’ (श. ब्रा. १० । ६ । ३ । २) इति । शारीरस्यात्मनो यः शब्दोऽभिधायकः सप्तम्यन्तः — अन्तरात्मन्निति ; तस्माद्विशिष्टोऽन्यः प्रथमान्तः पुरुषशब्दो मनोमयत्वादिविशिष्टस्यात्मनोऽभिधायकः । तस्मात्तयोर्भेदोऽधिगम्यते ॥ ५ ॥",
    "citations": [
      {
        "href": "",
        "text": "‘ यथा"
      }
    ]
  },
  {
    "source_url": "https://advaitasharada.sringeri.net/display/bhashya/BS/devanagari",
    "source_sha256": "3e25449a44a0e912318db91030eb2e604e0c4eb2f8b5ceaa4ff4f92ae5e5bb80",
    "chapter_id": "BS_C01",
    "section_id": "BS_C01_S02",
    "verse_id": "BS_C01_S02_V05",
    "block_id": "BS_C01_S02_V05_VERSETEXT_01",
    "block_type": "versetext",
    "text": "शब्दविशेषात् ॥ ५ ॥",
    "citations": []
  },
  {
    "source_url": "https://advaitasharada.sringeri.net/display/bhashya/BS/devanagari",
    "source_sha256": "3e25449a44a0e912318db91030eb2e604e0c4eb2f8b5ceaa4ff4f92ae5e5bb80",
    "chapter_id": "BS_C01",
    "section_id": "BS_C01_S02",
    "verse_id": "BS_C01_S02_V06",
    "block_id": "BS_C01_S02_V06_B1",
    "block_type": "bhashya",
    "text": "स्मृतिश्च शारीरपरमात्मनोर्भेदं दर्शयति — ‘ ईश्वरः सर्वभूतानां हृद्देशेऽर्जुन तिष्ठति । भ्रामयन्सर्वभूतानि यन्त्रारूढानि मायया ’ (भ. गी. १८ । ६१) इत्याद्या ।",
    "citations": [
      {
        "href": "Gita?id=BG_C18_V61",
        "text": "‘ ईश्वरः"
      }
    ]
  },
  {
    "source_url": "https://advaitasharada.sringeri.net/display/bhashya/BS/devanagari",
    "source_sha256": "3e25449a44a0e912318db91030eb2e604e0c4eb2f8b5ceaa4ff4f92ae5e5bb80",
    "chapter_id": "BS_C01",
    "section_id": "BS_C01_S02",
    "verse_id": "BS_C01_S02_V06",
    "block_id": "BS_C01_S02_V06_B2",
    "block_type": "bhashya",
    "text": "अत्राह — कः पुनरयं शारीरो नाम परमात्मनोऽन्यः , यः प्रतिषिध्यते — ‘ अनुपपत्तेस्तु न शारीरः ’ इत्यादिना ? श्रुतिस्तु ‘ नान्योऽतोऽस्ति द्रष्टा नान्योऽतोऽस्ति श्रोता ’ (बृ. उ. ३ । ७ । २३) इत्येवंजातीयका परमात्मनोऽन्यमात्मानं वारयति । तथा स्मृतिरपि ‘ क्षेत्रज्ञं चापि मां विद्धि सर्वक्षेत्रेषु भारत ’ (भ. गी. १३ । २) इत्येवंजातीयकेति । अत्रोच्यते — सत्य मे वैतत् , पर एवात्मा देहेन्द्रियमनोबुद्ध्युपाधिभिः परिच्छिद्यमानो बालैः शारीर इत्युपचर्यते । यथा घटकरकाद्युपाधिवशादपरिच्छिन्नमपि नभः परिच्छिन्नवदवभासते , तद्वत् । तदपेक्षया च कर्मत्वकर्तृत्वादिभेदव्यवहारो न विरुध्यते प्राक् ‘ तत्त्वमसि ’ इत्यात्मैकत्वोपदेशग्रहणात् । गृहीते त्वात्मैकत्वे बन्धमोक्षादिसर्वव्यवहारपरिसमाप्तिरेव स्यात् ॥ ६ ॥",
    "citations": [
      {
        "href": "Brha?id=BR_C03_S07_V23",
        "text": "‘ नान्योऽतोऽस्ति"
      },
      {
        "href": "Gita?id=BG_C13_V02",
        "text": "‘ क्षेत्रज्ञं"
      }
    ]
  },
  {
    "source_url": "https://advaitasharada.sringeri.net/display/bhashya/BS/devanagari",
    "source_sha256": "3e25449a44a0e912318db91030eb2e604e0c4eb2f8b5ceaa4ff4f92ae5e5bb80",
    "chapter_id": "BS_C01",
    "section_id": "BS_C01_S02",
    "verse_id": "BS_C01_S02_V06",
    "block_id": "BS_C01_S02_V06_VERSETEXT_01",
    "block_type": "versetext",
    "text": "स्मृतेश्च ॥ ६ ॥",
    "citations": []
  },
  {
    "source_url": "https://advaitasharada.sringeri.net/display/bhashya/BS/devanagari",
    "source_sha256": "3e25449a44a0e912318db91030eb2e604e0c4eb2f8b5ceaa4ff4f92ae5e5bb80",
    "chapter_id": "BS_C01",
    "section_id": "BS_C01_S02",
    "verse_id": "BS_C01_S02_V07",
    "block_id": "BS_C01_S02_V07_B1",
    "block_type": "bhashya",
    "text": "अर्भकमल्पम् ओको नीडम् , ‘ एष म आत्मान्तर्हृदये ’ इति परिच्छिन्नायतनत्वात् , स्वशब्देन च ‘ अणीयान्व्रीहेर्वा यवाद्वा ’ इत्यणीयस्त्वव्यपदेशात् , शारीर एवाराग्रमात्रो जीव इहोपदिश्यते , न सर्वगतः परमात्मा — इति यदुक्तं तत्परिहर्तव्यम् । अत्रोच्यते — नायं दोषः । न ताव त्परिच्छिन्नदेशस्य सर्वगतत्वव्यपदेशः कथम प्युपपद्यते । सर्वगतस्य तु सर्वदेशेषु विद्यमानत्वात्परिच्छिन्नदेशव्यपदेशोऽपि कयाचिदपेक्षया सम्भवति । यथा सम स्तवसुधाधिपतिरपि हि सन् अयोध्याधिपतिरिति व्यपदिश्यते । कया पुनरपेक्षया सर्वगतः सन्नीश्वरोऽर्भकौका अणीयांश्च व्यपदिश्यत इति । निचाय्यत्वादेवमिति ब्रूमः । एवम् अणीयस्त्वादिगुणगणोपेत ईश्वरः , तत्र हृदयपुण्डरीके निचाय्यो द्रष्टव्य उपदिश्यते ; यथा सालग्रामे हरिः । तत्रास्य बुद्धिविज्ञानं ग्राहकम् । सर्वगतोऽपीश्वरस्तत्रोपास्यमानः प्रसीदति । व्योमवच्चैतद्द्रष्टव्यम् । यथा सर्वगतमपि सद्व्योम सूचीपाशाद्यपेक्षयार्भकौकोऽणीयश्च व्यपदिश्यते , एवं ब्रह्मापि । तदेवं निचाय्यत्वापेक्षं ब्रह्मणोऽर्भकौकस्त्वमणीयस्त्वं च , न पारमार्थिकम् । तत्र यदाशङ्क्यते — हृदयायतनत्वाद्ब्रह्मणो हृदयानां च प्रतिशरीरं भिन्नत्वाद्भिन्नायतनानां च शुकादीनामनेकत्वसावयवत्वानित्यत्वादिदोषदर्शनाद्ब्रह्मणोऽपि तत्प्रसङ्ग इति , तदपि परिहृतं भवति ॥ ७ ॥",
    "citations": []
  },
  {
    "source_url": "https://advaitasharada.sringeri.net/display/bhashya/BS/devanagari",
    "source_sha256": "3e25449a44a0e912318db91030eb2e604e0c4eb2f8b5ceaa4ff4f92ae5e5bb80",
    "chapter_id": "BS_C01",
    "section_id": "BS_C01_S02",
    "verse_id": "BS_C01_S02_V07",
    "block_id": "BS_C01_S02_V07_VERSETEXT_01",
    "block_type": "versetext",
    "text": "अर्भकौकस्त्वात्तद्व्यपदेशाच्च नेति चेन्न निचाय्यत्वादेवं व्योमवच्च ॥ ७ ॥",
    "citations": []
  },
  {
    "source_url": "https://advaitasharada.sringeri.net/display/bhashya/BS/devanagari",
    "source_sha256": "3e25449a44a0e912318db91030eb2e604e0c4eb2f8b5ceaa4ff4f92ae5e5bb80",
    "chapter_id": "BS_C01",
    "section_id": "BS_C01_S02",
    "verse_id": "BS_C01_S02_V08",
    "block_id": "BS_C01_S02_V08_B1",
    "block_type": "bhashya",
    "text": "व्योमव त्सर्वगतस्य ब्रह्मणः सर्वप्राणिहृदयसम्बन्धात् , चिद्रूपतया च शारीरादविशिष्टत्वात् , सुखदुःखादिसम्भोगोऽप्यविशिष्टः प्रसज्येत । एकत्वाच्च ; न हि परस्मादात्मनोऽन्यः कश्चिदात्मा संसारी विद्यते , ‘ नान्योऽतोऽस्ति विज्ञाता ’ (बृ. उ. ३ । ७ । २३) इत्यादिश्रुतिभ्यः । तस्मात्परस्यैव ब्रह्मणः सम्भोगप्राप्तिरिति चेत् , न ; वैशेष्यात् । न तावत्सर्वप्राणिहृदयसम्बन्धात् शारीरवद्ब्रह्मणः सम्भोगप्रसङ्गः , वैशेष्यात् । विशेषो हि भवति शारीरपरमेश्वरयोः । एकः कर्ता भोक्ता धर्माधर्मादिसाधनः सुखदुःखादिमांश्च । एकस्तद्विपरीतोऽपहतपाप्मत्वादिगुणः । एतस्मादनयोर्विशेषादेकस्य भोगः , नेतरस्य । यदि च सन्निधानमात्रेण वस्तुशक्तिमनाश्रित्य कार्यसम्बन्धोऽभ्युपगम्येत , आकाशादीनामपि दाहादिप्रसङ्गः । सर्वग ता नेकात्मवादिनामपि समावेतौ चोद्यपरिहारौ । यदप्येकत्वाद्ब्रह्मण आत्मान्तराभावाच्छारीरस्य भोगेन ब्रह्मणो भोगप्रसङ्ग इति , अत्र वदामः — इदं तावद्देवानांप्रियः प्रष्टव्यः ; कथमयं त्वयात्मान्तराभावोऽध्यवसित इति । ‘ तत्त्वमसि ’ ‘ अहं ब्रह्मास्मि ’ ‘ नान्योऽतोऽस्ति विज्ञाता ’ इत्यादिशास्त्रेभ्य इति चेत् , यथाशास्त्रं तर्हि शास्त्रीयोऽर्थः प्रतिपत्तव्यः , न तत्रार्धजरतीयं लभ्यम् । शास्त्रं च ‘ तत्त्वमसि ’ इत्यपहतपाप्मत्वादिविशेषणं ब्रह्म शारीरस्यात्मत्वेनोपदिशच्छारीरस्यैव तावदुपभोक्तृत्वं वारयति । कुतस्तदुपभोगेन ब्रह्मण उपभोगप्रसङ्गः । अथागृहीतं शारीरस्य ब्रह्मणैकत्वम् , तदा मिथ्याज्ञाननिमित्तः शारीरस्योपभोगः । न तेन परमार्थरूपस्य ब्रह्मणः संस्पर्शः । न हि बालैस्तलमलिनतादिभिर्व्योम्नि विकल्प्यमाने तलमलिनतादिविशिष्टमेव परमार्थतो व्योम भवति । तदाह — न वैशेष्यादिति नैकत्वेऽपि शारीरस्योपभोगेन ब्रह्मण उपभोगप्रसङ्गः , वैशेष्यात् । विशेषो हि भवति मिथ्याज्ञानसम्यग्ज्ञानयोः । मिथ्याज्ञानकल्पित उपभोगः , सम्यग्ज्ञानदृष्टमेकत्वम् । न च मिथ्याज्ञानकल्पितेनोपभोगेन सम्यग्ज्ञानदृष्टं वस्तु संस्पृश्यते । तस्मान्नोपभोगगन्धोऽपि शक्य ईश्वरस्य कल्पयितुम् ॥ ८ ॥",
    "citations": [
      {
        "href": "Brha?id=BR_C03_S07_V23",
        "text": "‘ नान्योऽतोऽस्ति"
      }
    ]
  },
  {
    "source_url": "https://advaitasharada.sringeri.net/display/bhashya/BS/devanagari",
    "source_sha256": "3e25449a44a0e912318db91030eb2e604e0c4eb2f8b5ceaa4ff4f92ae5e5bb80",
    "chapter_id": "BS_C01",
    "section_id": "BS_C01_S02",
    "verse_id": "BS_C01_S02_V08",
    "block_id": "BS_C01_S02_V08_VERSETEXT_01",
    "block_type": "versetext",
    "text": "सम्भोगप्राप्तिरिति चेन्न वैशेष्यात् ॥ ८ ॥",
    "citations": []
  },
  {
    "source_url": "https://advaitasharada.sringeri.net/display/bhashya/BS/devanagari",
    "source_sha256": "3e25449a44a0e912318db91030eb2e604e0c4eb2f8b5ceaa4ff4f92ae5e5bb80",
    "chapter_id": "BS_C01",
    "section_id": "BS_C01_S02",
    "verse_id": "BS_C01_S02_V09",
    "block_id": "BS_C01_S02_V09_B1",
    "block_type": "bhashya",
    "text": "कठवल्लीषु पठ्यते ‘ यस्य ब्रह्म च क्षत्रं चोभे भवत ओदनः । मृत्युर्यस्योपसेचनं क इत्था वेद यत्र सः ’ (क. उ. १ । २ । २५) इति । अत्र कश्चिदोदनोपसेचनसूचितोऽत्ता प्रतीयते । तत्र किमग्निरत्ता स्यात् , उत जीवः , अथवा परमात्मा , इति संशयः । विशे षा नवधारणात् । त्रयाणां चाग्निजीवपरमात्मनामस्मिन्ग्रन्थे प्रश्नोपन्यासोपलब्धेः । किं ताव त्प्राप्तम् ? अग्निरत्तेति । कुतः ? ‘ अग्निरन्नादः ’ (बृ. उ. १ । ४ । ६) इति श्रुतिप्रसिद्धिभ्याम् । जीवो वा अत्ता स्यात् ‘ तयोरन्यः पिप्पलं स्वाद्वत्ति ’ (मु. उ. ३ । १ । १) इति दर्शनात् । न परमात्मा , ‘ अनश्नन्नन्योऽभिचाकशीति ’ इति दर्शनादित्येवं प्राप्ते ब्रूमः —",
    "citations": [
      {
        "href": "Kathaka?id=Ka_C01_S02_V25",
        "text": "‘ यस्य"
      },
      {
        "href": "Brha?id=BR_C01_S04_V06",
        "text": "‘ अग्निरन्नादः"
      },
      {
        "href": "Mundaka?id=MD_C03_S01_V01",
        "text": "‘ तयोरन्यः"
      }
    ]
  },
  {
    "source_url": "https://advaitasharada.sringeri.net/display/bhashya/BS/devanagari",
    "source_sha256": "3e25449a44a0e912318db91030eb2e604e0c4eb2f8b5ceaa4ff4f92ae5e5bb80",
    "chapter_id": "BS_C01",
    "section_id": "BS_C01_S02",
    "verse_id": "BS_C01_S02_V09",
    "block_id": "BS_C01_S02_V09_B2",
    "block_type": "bhashya",
    "text": "अत्तात्र परमात्मा भवितुमर्हति । कुतः ? चराचरग्रहणात् । चराचरं हि स्थावरजङ्गमं मृत्यूपसेचनमिहाद्यत्वेन प्रतीयते । तादृशस्य चाद्यस्य न परमात्मनोऽन्यः कार्त्स्न्येनात्ता सम्भवति । परमात्मा तु विकारजातं संहरन्सर्वमत्तीत्युपपद्यते । नन्विह चराचरग्रहणं नोपलभ्यते , कथं सिद्धवच्चराचरग्रहणं हेतुत्वेनोपादीयते ? नैष दोषः , मृत्यूपसेचनत्वेनेहाद्यत्वेन सर्वस्य प्राणिनिकायस्य प्रतीयमानत्वात् , ब्रह्मक्षत्रयोश्च प्राधान्यात्प्रदर्शनार्थत्वोपपत्तेः । यत्तु परमात्मनोऽपि नात्तृत्वं सम्भवति ‘ अनश्नन्नन्योऽभिचाकशीति ’ इति दर्शनादिति , अत्रोच्यते — कर्मफलभोगस्य प्रतिषेधकमेतद्दर्शनम् , तस्य सन्निहितत्वात् । न विकारसंहारस्य प्रतिषेधकम् , सर्ववेदान्तेषु सृष्टिस्थितिसंहारकारणत्वेन ब्रह्मणः प्रसिद्धत्वात् । तस्मात्परमात्मैवेहात्ता भवितुमर्हति ॥ ९ ॥",
    "citations": []
  },
  {
    "source_url": "https://advaitasharada.sringeri.net/display/bhashya/BS/devanagari",
    "source_sha256": "3e25449a44a0e912318db91030eb2e604e0c4eb2f8b5ceaa4ff4f92ae5e5bb80",
    "chapter_id": "BS_C01",
    "section_id": "BS_C01_S02",
    "verse_id": "BS_C01_S02_V09",
    "block_id": "BS_C01_S02_V09_VERSETEXT_01",
    "block_type": "versetext",
    "text": "अत्ता चराचरग्रहणात् ॥ ९ ॥",
    "citations": []
  },
  {
    "source_url": "https://advaitasharada.sringeri.net/display/bhashya/BS/devanagari",
    "source_sha256": "3e25449a44a0e912318db91030eb2e604e0c4eb2f8b5ceaa4ff4f92ae5e5bb80",
    "chapter_id": "BS_C01",
    "section_id": "BS_C01_S02",
    "verse_id": "BS_C01_S02_V10",
    "block_id": "BS_C01_S02_V10_B1",
    "block_type": "bhashya",
    "text": "इतश्च परमात्मैवेहात्ता भवितुमर्हति ; यत्कारणं प्रकरणमिदं परमात्मनः — ‘ न जायते म्रियते वा विपश्चित् ’ (क. उ. १ । २ । १८) इत्यादि । प्रकृतग्रहणं च न्याय्यम् । ‘ क इत्था वेद यत्र सः ’ इति च दुर्विज्ञानत्वं परमात्मलिङ्गम् ॥ १० ॥",
    "citations": [
      {
        "href": "Kathaka?id=Ka_C01_S02_V18",
        "text": "‘ न"
      }
    ]
  },
  {
    "source_url": "https://advaitasharada.sringeri.net/display/bhashya/BS/devanagari",
    "source_sha256": "3e25449a44a0e912318db91030eb2e604e0c4eb2f8b5ceaa4ff4f92ae5e5bb80",
    "chapter_id": "BS_C01",
    "section_id": "BS_C01_S02",
    "verse_id": "BS_C01_S02_V10",
    "block_id": "BS_C01_S02_V10_VERSETEXT_01",
    "block_type": "versetext",
    "text": "प्रकरणाच्च ॥ १० ॥",
    "citations": []
  },
  {
    "source_url": "https://advaitasharada.sringeri.net/display/bhashya/BS/devanagari",
    "source_sha256": "3e25449a44a0e912318db91030eb2e604e0c4eb2f8b5ceaa4ff4f92ae5e5bb80",
    "chapter_id": "BS_C01",
    "section_id": "BS_C01_S02",
    "verse_id": "BS_C01_S02_V11",
    "block_id": "BS_C01_S02_V11_B1",
    "block_type": "bhashya",
    "text": "कठवल्लीष्वेव पठ्यते — ‘ ऋतं पिबन्तौ सुकृतस्य लोके गुहां प्रविष्टौ परमे परार्धे । छायातपौ ब्रह्मविदो वदन्ति पञ्चाग्नयो ये च त्रिणाचिकेताः ’ (क. उ. १ । ३ । १) इति । तत्र संशयः — किमिह बुद्धिजीवौ निर्दिष्टौ , उत जीवपरमात्मानाविति । यदि बुद्धिजीवौ , ततो बुद्धिप्रधानात्कार्यकरणसङ्घाताद्विलक्षणो जीवः प्रतिपादितो भवति । तदपीह प्रतिपादयितव्यम् , ‘ येयं प्रेते विचिकित्सा मनुष्येऽस्तीत्येके नायमस्तीति चैके । एतद्विद्यामनुशिष्टस्त्वयाहं वराणामेष वरस्तृतीयः ’ (क. उ. १ । १ । २०) इति पृष्टत्वात् । अथ जीवपरमात्मानौ , ततो जीवाद्विलक्षणः परमात्मा प्रतिपादितो भवति । तदपीह प्रतिपादयितव्यम् — ‘ अन्यत्र धर्मादन्यत्राधर्मादन्यत्रास्मात्कृताकृतात् । अन्यत्र भूताच्च भव्याच्च यत्तत्पश्यसि तद्वद ’ (क. उ. १ । २ । १४) इति पृष्टत्वात् । अत्रा हा क्षेप्ता — उभावप्येतौ पक्षौ न सम्भवतः । कस्मात् ? ऋतपानं कर्मफलोपभोगः , ‘ सुकृतस्य लोके ’ इति लिङ्गात् । तच्च चेतनस्य क्षेत्रज्ञस्य सम्भवति , नाचेतनाया बुद्धेः । ‘ पिबन्तौ ’ इति च द्विवचनेन द्वयोः पानं दर्शयति श्रुतिः । अतो बुद्धिक्षेत्रज्ञपक्षस्तावन्न सम्भवति । अत एव क्षेत्रज्ञपरमात्मपक्षोऽपि न सम्भवति । चेतनेऽपि परमात्मनि ऋतपानासम्भवात् , ‘ अनश्नन्नन्योऽभिचाकशीति ’ (मु. उ. ३ । १ । १) इति मन्त्रवर्णादिति । अत्रोच्यते — नैष दोषः ; छत्रिणो गच्छन्तीत्येकेनापि च्छत्रिणा बहूनामच्छत्रिणां छत्रित्वोपचारदर्शनात् । एवमेकेनापि पिबता द्वौ पिबन्तावुच्येयाताम् । यद्वा जीवस्तावत्पिबति । ईश्वरस्तु पाययति । पाययन्नपि पिबतीत्युच्यते , पाचयितर्यपि पक्तृत्वप्रसिद्धिदर्शनात् । बुद्धि क्षेत्रज्ञपरिग्रहोऽपि सम्भवति ; करणे कर्तृत्वोपचारात् । ‘ एधांसि पचन्ति ’ इति प्रयोगदर्शनात् । न चा ध्यात्माधिकारेऽन्यौ कौचिद्द्वावृतं पिबन्तौ सम्भवतः । तस्माद्बुद्धिजीवौ स्यातां जीवपरमात्मानौ वेति संशयः ॥",
    "citations": [
      {
        "href": "Kathaka?id=Ka_C01_S03_V01",
        "text": "‘ ऋतं"
      },
      {
        "href": "Kathaka?id=Ka_C01_S01_V20",
        "text": "‘ येयं"
      },
      {
        "href": "Kathaka?id=Ka_C01_S02_V14",
        "text": "‘ अन्यत्र"
      },
      {
        "href": "Mundaka?id=MD_C03_S01_V01",
        "text": "‘ अनश्नन्नन्योऽभिचाकशीति"
      }
    ]
  },
  {
    "source_url": "https://advaitasharada.sringeri.net/display/bhashya/BS/devanagari",
    "source_sha256": "3e25449a44a0e912318db91030eb2e604e0c4eb2f8b5ceaa4ff4f92ae5e5bb80",
    "chapter_id": "BS_C01",
    "section_id": "BS_C01_S02",
    "verse_id": "BS_C01_S02_V11",
    "block_id": "BS_C01_S02_V11_B2",
    "block_type": "bhashya",
    "text": "किं ताव त्प्राप्तम् ? बुद्धिक्षेत्रज्ञाविति । कुतः ? ‘ गुहां प्रविष्टौ ’ इति विशेषणात् । यदि शरीरं गुहा , यदि वा हृदयम् , उभयथापि बुद्धिक्षेत्रज्ञौ गुहां प्रविष्टावुपपद्येते । न च सति सम्भवे सर्वगतस्य ब्रह्मणो विशिष्टदेशत्वं युक्तं कल्पयितुम् । ‘ सुकृतस्य लोके ’ इति च कर्मगोचरानतिक्रमं दर्शयति । परमात्मा तु न सुकृतस्य वा दुष्कृतस्य वा गोचरे वर्तते , ‘ न कर्मणा वर्धते नो कनीयान् ’ (बृ. उ. ४ । ४ । २३) इति श्रुतेः । ‘ छायातपौ ’ इति च चेतनाचेतनयोर्निर्देश उपपद्यते , छायातपवत्परस्परविलक्षणत्वात् । तस्माद्बुद्धिक्षेत्रज्ञाविहोच्येयातामित्येवं प्राप्ते ब्रूमः —",
    "citations": [
      {
        "href": "Brha?id=BR_C04_S04_V23",
        "text": "‘ न"
      }
    ]
  },
  {
    "source_url": "https://advaitasharada.sringeri.net/display/bhashya/BS/devanagari",
    "source_sha256": "3e25449a44a0e912318db91030eb2e604e0c4eb2f8b5ceaa4ff4f92ae5e5bb80",
    "chapter_id": "BS_C01",
    "section_id": "BS_C01_S02",
    "verse_id": "BS_C01_S02_V11",
    "block_id": "BS_C01_S02_V11_B3",
    "block_type": "bhashya",
    "text": "विज्ञानात्मपरमात्मानाविहोच्येयाताम् । कस्मात् ? आत्मानौ हि तावुभावपि चेतनौ समानस्वभावौ । संख्याश्रवणे च समानस्वभावेष्वेव लोके प्रतीतिर्दृश्यते । ‘ अस्य गोर्द्वितीयोऽन्वेष्टव्यः ’ इत्युक्ते , गौरेव द्वितीयोऽन्विष्यते , नाश्वः पुरुषो वा । तदिह ऋतपानेन लिङ्गेन निश्चिते विज्ञानात्मनि द्वितीयान्वेषणायां समानस्वभावश्चेतनः परमात्मैव प्रतीयते । ननूक्तं गुहाहितत्वदर्शनान्न परमात्मा प्रत्येतव्य इति ; गुहाहितत्वदर्शनादेव परमात्मा प्रत्येतव्य इति वदामः । गुहाहितत्वं तु श्रुतिस्मृतिष्वसकृत्परमात्मन एव दृश्यते — ‘ गुहाहितं गह्वरेष्ठं पुराणम् ’ (क. उ. १ । २ । १२) ‘ यो वेद निहितं गुहायां परमे व्योमन् ’ (तै. उ. २ । १ । १) ‘ आत्मानमन्विच्छ गुहां प्रविष्टम् ’ इत्याद्यासु । सर्वगतस्यापि ब्रह्मण उपलब्ध्यर्थो देशविशेषोपदेशो न विरुध्यत इत्येतदप्युक्तमेव । सुकृतलोकवर्तित्वं तु च्छत्रित्ववदेकस्मिन्नपि वर्तमानमुभयोरविरुद्धम् । ‘ छायातपौ ’ इत्यप्यविरुद्धम् ; छायातपवत्परस्परविलक्षणत्वात्संसारित्वासंसारित्वयोः , अविद्याकृतत्वात्संसारित्वस्य पारमार्थिकत्वाच्चासंसारित्वस्य । तस्माद्विज्ञानात्मपरमात्मानौ गुहां प्रविष्टौ गृह्येते ॥ ११ ॥",
    "citations": [
      {
        "href": "Kathaka?id=Ka_C01_S02_V12",
        "text": "‘ गुहाहितं"
      },
      {
        "href": "Taitiriya?id=T_C02_S01_V01",
        "text": "‘ यो"
      }
    ]
  },
  {
    "source_url": "https://advaitasharada.sringeri.net/display/bhashya/BS/devanagari",
    "source_sha256": "3e25449a44a0e912318db91030eb2e604e0c4eb2f8b5ceaa4ff4f92ae5e5bb80",
    "chapter_id": "BS_C01",
    "section_id": "BS_C01_S02",
    "verse_id": "BS_C01_S02_V11",
    "block_id": "BS_C01_S02_V11_VERSETEXT_01",
    "block_type": "versetext",
    "text": "गुहां प्रविष्टावात्मानौ हि तद्दर्शनात् ॥ ११ ॥",
    "citations": []
  },
  {
    "source_url": "https://advaitasharada.sringeri.net/display/bhashya/BS/devanagari",
    "source_sha256": "3e25449a44a0e912318db91030eb2e604e0c4eb2f8b5ceaa4ff4f92ae5e5bb80",
    "chapter_id": "BS_C01",
    "section_id": "BS_C01_S02",
    "verse_id": "BS_C01_S02_V12",
    "block_id": "BS_C01_S02_V12_B1",
    "block_type": "bhashya",
    "text": "विशेषणं च विज्ञानात्मपरमात्मनोरेव भवति । ‘ आत्मानं रथिनं विद्धि शरीरं रथमेव तु ’ (क. उ. १ । ३ । ३) इत्यादिना परेण ग्रन्थेन रथिरथादिरूपककल्पनया विज्ञानात्मानं रथिनं संसारमोक्षयोर्गन्तारं कल्पयति । ‘ सोऽध्वनः पारमाप्नोति तद्विष्णोः परमं पदम् ’ (क. उ. १ । ३ । ९) इति च परमात्मानं गन्तव्यं कल्पयति । तथा ‘ तं दुर्दर्शं गूढमनुप्रविष्टं गुहाहितं गह्वरेष्ठं पुराणम् । अध्यात्मयोगाधिगमेन देवं मत्वा धीरो हर्षशोकौ जहाति ’ (क. उ. १ । २ । १२) इति पूर्वस्मिन्नपि ग्रन्थे मन्तृमन्तव्यत्वेनैतावेव विशेषितौ । प्रकरणं चेदं परमात्मनः । ‘ ब्रह्मविदो वदन्ति ’ इति च वक्तृविशेषोपादानं परमात्मपरिग्रहे घटते । तस्मादिह जीवपरमात्मानावुच्येयाताम् । एष एव न्यायः ‘ द्वा सुपर्णा सयुजा सखाया ’ (मु. उ. ३ । १ । १) इत्येवमादिष्वपि । तत्रापि ह्यध्यात्माधिकारान्न प्राकृतौ सुपर्णावुच्येते । ‘ तयोरन्यः पिप्पलं स्वाद्वत्ति ’ इत्यदनलिङ्गाद्विज्ञानात्मा भवति । ‘ अनश्नन्नन्योऽभिचाकशीति ’ (मु. उ. ३ । १ । १) इत्यनशनचेतनत्वाभ्यां परमात्मा । अनन्तरे च मन्त्रे तावेव द्रष्टृद्रष्टव्यभावेन विशिनष्टि — ‘ समाने वृक्षे पुरुषो निमग्नोऽनीशया शोचति मुह्यमानः । जुष्टं यदा पश्यत्यन्यमीशमस्य महिमानमिति वीतशोकः ’ (मु. उ. ३ । १ । २) इति ॥",
    "citations": [
      {
        "href": "Kathaka?id=Ka_C01_S03_V03",
        "text": "‘ आत्मानं"
      },
      {
        "href": "Kathaka?id=Ka_C01_S03_V09",
        "text": "‘ सोऽध्वनः"
      },
      {
        "href": "Kathaka?id=Ka_C01_S02_V12",
        "text": "‘ तं"
      },
      {
        "href": "Mundaka?id=MD_C03_S01_V01",
        "text": "‘ द्वा"
      },
      {
        "href": "Mundaka?id=MD_C03_S01_V01",
        "text": "‘ अनश्नन्नन्योऽभिचाकशीति"
      },
      {
        "href": "Mundaka?id=MD_C03_S01_V02",
        "text": "‘ समाने"
      }
    ]
  },
  {
    "source_url": "https://advaitasharada.sringeri.net/display/bhashya/BS/devanagari",
    "source_sha256": "3e25449a44a0e912318db91030eb2e604e0c4eb2f8b5ceaa4ff4f92ae5e5bb80",
    "chapter_id": "BS_C01",
    "section_id": "BS_C01_S02",
    "verse_id": "BS_C01_S02_V12",
    "block_id": "BS_C01_S02_V12_B2",
    "block_type": "bhashya",
    "text": "अपर आह — ‘ द्वा सुपर्णा ’ इति नेयमृगस्याधिकरणस्य सिद्धान्तं भजते , पैङ्गिरहस्यब्राह्मणेनान्यथा व्याख्यातत्वात् — ‘ तयोरन्यः पिप्पलं स्वाद्वत्तीति सत्त्वमनश्नन्नन्योऽभिचाकशीतीत्यनश्नन्नन्योऽभिपश्यति ज्ञस्तावेतौ सत्त्वक्षेत्रज्ञौ ’ इति । सत्त्वशब्दो जीवः क्षेत्रज्ञशब्दः परमात्मेति यदुच्यते , तन्न ; सत्त्वक्षेत्रज्ञशब्दयोरन्तःकरणशारीरपरतया प्रसिद्धत्वात् । तत्रैव च व्याख्यातत्वात् — ‘ तदेतत्सत्त्वं येन स्वप्नं पश्यति , अथ योऽयं शारीर उपद्रष्टा स क्षेत्रज्ञस्तावेतौ सत्त्वक्षेत्रज्ञौ ’ इति । ना प्य स्याधिकरणस्य पूर्वपक्षं भजते । न ह्यत्र शारीरः क्षेत्रज्ञः कर्तृत्वभोक्तृत्वादिना संसारधर्मेणोपेतो विवक्ष्यते । कथं तर्हि ? सर्वसंसारधर्मातीतो ब्रह्मस्वभावश्चैतन्यमात्रस्वरूपः ; ‘ अनश्नन्नन्योऽभिचाकशीतीत्यनश्नन्नन्योऽभिपश्यति ज्ञः ’ इति वचनात् , ‘ तत्त्वमसि ’ ‘ क्षेत्रज्ञं चापि मां विद्धि ’ (भ. गी. १३ । २) इत्यादिश्रुतिस्मृतिभ्यश्च । तावता च विद्योपसंहारदर्शनमेवमेवावकल्पते , ‘ तावेतौ सत्त्वक्षेत्रज्ञौ न ह वा एवंविदि किञ्चन रज आध्वंसते ’ इत्यादि । कथं पुनरस्मिन्पक्षे ‘ तयोरन्यः पिप्पलं स्वाद्वत्तीति सत्त्वम् ’ इत्यचेतने सत्त्वे भोक्तृत्ववचनमिति , उच्यते — नेयं श्रुतिरचेतनस्य सत्त्वस्य भोक्तृत्वं वक्ष्यामीति प्रवृत्ता ; किं तर्हि ? चेतनस्य क्षेत्रज्ञस्याभोक्तृत्वं ब्रह्मस्वभावतां च वक्ष्यामीति । तदर्थं सुखादिविक्रियावति सत्त्वे भोक्तृत्वमध्यारोपयति । इदं हि कर्तृत्वं भोक्तृत्वं च सत्त्वक्षेत्रज्ञयोरितरेतरस्वभावाविवेककृतं कल्प्यते । परमार्थतस्तु नान्यतरस्यापि सम्भवति , अचेतनत्वात्सत्त्वस्य , अविक्रियत्वाच्च क्षेत्रज्ञस्य । अविद्याप्रत्युपस्थापितस्वभावत्वाच्च सत्त्वस्य सुतरां न सम्भवति । तथा च श्रुतिः — ‘ यत्र वा अन्यदिव स्यात्तत्रान्योऽन्यत्पश्येत् ’ (बृ. उ. ४ । ५ । १५) इत्यादिना स्वप्नदृष्टहस्त्यादिव्यवहारवदविद्याविषय एव कर्तृत्वादिव्यवहारं दर्शयति । ‘ यत्र त्वस्य सर्वमात्मैवाभूत्तत्केन कं पश्येत् ’ (बृ. उ. ४ । ५ । १५) इत्यादिना च विवेकिनः कर्तृत्वादिव्यवहाराभवं दर्शयति ॥ १२ ॥",
    "citations": [
      {
        "href": "Gita?id=BG_C13_V02",
        "text": "‘ क्षेत्रज्ञं"
      },
      {
        "href": "Brha?id=BR_C04_S03_V31",
        "text": "‘ यत्र"
      },
      {
        "href": "Brha?id=BR_C04_S05_V15",
        "text": "‘ यत्र"
      }
    ]
  },
  {
    "source_url": "https://advaitasharada.sringeri.net/display/bhashya/BS/devanagari",
    "source_sha256": "3e25449a44a0e912318db91030eb2e604e0c4eb2f8b5ceaa4ff4f92ae5e5bb80",
    "chapter_id": "BS_C01",
    "section_id": "BS_C01_S02",
    "verse_id": "BS_C01_S02_V12",
    "block_id": "BS_C01_S02_V12_I01",
    "block_type": "leading_bhashya",
    "text": "कुतश्च विज्ञानात्मपरमात्मानौ गृह्येते ? —",
    "citations": []
  },
  {
    "source_url": "https://advaitasharada.sringeri.net/display/bhashya/BS/devanagari",
    "source_sha256": "3e25449a44a0e912318db91030eb2e604e0c4eb2f8b5ceaa4ff4f92ae5e5bb80",
    "chapter_id": "BS_C01",
    "section_id": "BS_C01_S02",
    "verse_id": "BS_C01_S02_V12",
    "block_id": "BS_C01_S02_V12_VERSETEXT_01",
    "block_type": "versetext",
    "text": "विशेषणाच्च ॥ १२ ॥",
    "citations": []
  },
  {
    "source_url": "https://advaitasharada.sringeri.net/display/bhashya/BS/devanagari",
    "source_sha256": "3e25449a44a0e912318db91030eb2e604e0c4eb2f8b5ceaa4ff4f92ae5e5bb80",
    "chapter_id": "BS_C01",
    "section_id": "BS_C01_S02",
    "verse_id": "BS_C01_S02_V13",
    "block_id": "BS_C01_S02_V13_B1",
    "block_type": "bhashya",
    "text": "‘ य एषोऽक्षिणि पुरुषो दृश्यत एष आत्मेति होवाचैतदमृतमभयमेतद्ब्रह्मेति । तद्यद्यप्यस्मिन्सर्पिर्वोदकं वा सिञ्चति वर्त्मनी एव गच्छति ’ (छा. उ. ४ । १५ । १) इत्यादि श्रूयते । तत्र संशयः — किमयं प्रतिबिम्बात्माक्ष्यधिकरणो निर्दिश्यते , अथ विज्ञानात्मा , उत देवतात्मेन्द्रियस्याधिष्ठाता , अथवेश्वर इति । किं तावत्प्राप्तम् ? छायात्मा पुरुषप्रतिरूप इति । कुतः ? तस्य दृश्यमानत्वप्रसिद्धेः , ‘ य एषोऽक्षिणि पुरुषो दृश्यते ’ इति च प्रसिद्धव दु पदेशात् । विज्ञानात्मनो वायं निर्देश इति युक्तम् । स हि चक्षुषा रूपं पश्यंश्चक्षुषि सन्निहितो भवति । आत्मशब्दश्चास्मिन्पक्षेऽनुकूलो भवति । आदित्यपुरुषो वा चक्षुषोऽनुग्राहकः प्रतीयते — ‘ रश्मिभिरेषोऽस्मिन्प्रतिष्ठितः ’ (बृ. उ. ५ । ५ । २) इति श्रुतेः , अमृतत्वादीनां च देवतात्मन्यपि कथञ्चित्सम्भवात् । नेश्वरः , स्थानविशेषनिर्देशात् — इत्येवं प्राप्ते ब्रूमः —",
    "citations": [
      {
        "href": "Chandogya?id=Ch_C04_S15_V01",
        "text": "‘ य"
      },
      {
        "href": "Brha?id=BR_C05_S05_V02",
        "text": "‘ रश्मिभिरेषोऽस्मिन्प्रतिष्ठितः"
      }
    ]
  },
  {
    "source_url": "https://advaitasharada.sringeri.net/display/bhashya/BS/devanagari",
    "source_sha256": "3e25449a44a0e912318db91030eb2e604e0c4eb2f8b5ceaa4ff4f92ae5e5bb80",
    "chapter_id": "BS_C01",
    "section_id": "BS_C01_S02",
    "verse_id": "BS_C01_S02_V13",
    "block_id": "BS_C01_S02_V13_B2",
    "block_type": "bhashya",
    "text": "परमेश्वर ए वा क्षिण्यभ्यन्तरः पुरुष इहोपदिष्ट इति । कस्मात् ? उपपत्तेः । उपपद्यते हि परमेश्वरे गुणजातमिहोपदिश्यमानम् । आत्मत्वं तावन्मुख्यया वृत्त्या परमेश्वरे उपपद्यते , ‘ स आत्मा तत्त्वमसि ’ इति श्रुतेः । अमृतत्वाभयत्वे च तस्मिन्नसकृच्छ्रुतौ श्रूयेते । तथा परमेश्वरानुरूपमेतदक्षिस्थानम् । यथा हि परमेश्वरः सर्वदोषैरलिप्तः , अपहतपाप्मत्वादिश्रवणात् ; तथाक्षिस्थानं सर्वलेपरहितमुपदिष्टम् ‘ तद्यद्यप्यस्मिन्सर्पिर्वोदकं वा सिञ्चति , वर्त्मनी एव गच्छति ’ इति श्रुतेः । संयद्वामत्वादिगुणोपदेशश्च तस्मिन्नवकल्पते । ‘ एतं संयद्वाम इत्याचक्षते । एतं हि सर्वाणि वामान्यभिसंयन्ति’ , (छा. उ. ४ । १५ । २) ‘ एष उ एव वामनी रे ष हि सर्वाणि वामानि नयति ।’ (छा. उ. ४ । १५ । ३) ‘ एष उ एव भामनी रे ष हि सर्वेषु लोकेषु भाति ’ (छा. उ. ४ । १५ । ४) इति च । अत उपपत्तेरन्तरः परमेश्वरः ॥ १३ ॥",
    "citations": [
      {
        "href": "Chandogya?id=Ch_C04_S15_V02",
        "text": "‘ एतं"
      },
      {
        "href": "Chandogya?id=Ch_C04_S15_V03",
        "text": "‘ एष"
      },
      {
        "href": "Chandogya?id=Ch_C04_S15_V04",
        "text": "‘ एष"
      }
    ]
  },
  {
    "source_url": "https://advaitasharada.sringeri.net/display/bhashya/BS/devanagari",
    "source_sha256": "3e25449a44a0e912318db91030eb2e604e0c4eb2f8b5ceaa4ff4f92ae5e5bb80",
    "chapter_id": "BS_C01",
    "section_id": "BS_C01_S02",
    "verse_id": "BS_C01_S02_V13",
    "block_id": "BS_C01_S02_V13_VERSETEXT_01",
    "block_type": "versetext",
    "text": "अन्तर उपपत्तेः ॥ १३ ॥",
    "citations": []
  },
  {
    "source_url": "https://advaitasharada.sringeri.net/display/bhashya/BS/devanagari",
    "source_sha256": "3e25449a44a0e912318db91030eb2e604e0c4eb2f8b5ceaa4ff4f92ae5e5bb80",
    "chapter_id": "BS_C01",
    "section_id": "BS_C01_S02",
    "verse_id": "BS_C01_S02_V14",
    "block_id": "BS_C01_S02_V14_B1",
    "block_type": "bhashya",
    "text": "कथं पुनराकाशवत्सर्वगतस्य ब्रह्मणोऽक्ष्यल्पं स्थानमुपपद्यत इति , अत्रोच्यते — भवेदेषानवकॢप्तिः , यद्येतदेवैकं स्थानमस्य निर्दिष्टं भवेत् । सन्ति ह्यन्यान्यपि पृथिव्यादीनि स्थानान्यस्य निर्दिष्टानि — ‘ यः पृथिव्यां तिष्ठन् ’ (बृ. उ. ३ । ७ । ३) इत्यादिना । तेषु हि चक्षुरपि निर्दिष्टम् ‘ यश्चक्षुषि तिष्ठन् ’ इति । स्थानादिव्यपदेशादित्यादिग्रहणेनैतद्दर्शयति — न केवलं स्थानमेवैकमनुचितं ब्रह्मणो निर्दिश्यमानं दृश्यते । किं तर्हि ? नाम रूपमित्येवंजातीयकमप्यनामरूपस्य ब्रह्मणोऽनुचितं निर्दिश्यमानं दृश्यते — ‘ तस्योदिति नाम ’ (छा. उ. १ । ६ । ७) ‘ हिरण्यश्मश्रुः ’ इत्यादि । निर्गुणमपि सद्ब्रह्म नामरूपगतैर्गुणैः सगुणमुपासनार्थं तत्र तत्रोपदिश्यत इत्येतदप्युक्तमेव । सर्वगतस्यापि ब्रह्मण उपलब्ध्यर्थं स्थानविशेषो न विरुध्यते , सालग्राम इव विष्णोरित्येतदप्युक्तमेव ॥ १४ ॥",
    "citations": [
      {
        "href": "Brha?id=BR_C03_S07_V03",
        "text": "‘ यः"
      },
      {
        "href": "Chandogya?id=Ch_C01_S06_V07",
        "text": "‘ तस्योदिति"
      }
    ]
  },
  {
    "source_url": "https://advaitasharada.sringeri.net/display/bhashya/BS/devanagari",
    "source_sha256": "3e25449a44a0e912318db91030eb2e604e0c4eb2f8b5ceaa4ff4f92ae5e5bb80",
    "chapter_id": "BS_C01",
    "section_id": "BS_C01_S02",
    "verse_id": "BS_C01_S02_V14",
    "block_id": "BS_C01_S02_V14_VERSETEXT_01",
    "block_type": "versetext",
    "text": "स्थानादिव्यपदेशाच्च ॥ १४ ॥",
    "citations": []
  },
  {
    "source_url": "https://advaitasharada.sringeri.net/display/bhashya/BS/devanagari",
    "source_sha256": "3e25449a44a0e912318db91030eb2e604e0c4eb2f8b5ceaa4ff4f92ae5e5bb80",
    "chapter_id": "BS_C01",
    "section_id": "BS_C01_S02",
    "verse_id": "BS_C01_S02_V15",
    "block_id": "BS_C01_S02_V15_B1",
    "block_type": "bhashya",
    "text": "अपि च नैवात्र विवदितव्यम् — किं ब्रह्मास्मिन्वाक्येऽभिधीयते , न वेति । सुखविशिष्टाभिधानादेव ब्रह्मत्वं सिद्धम् । सुखविशिष्टं हि ब्रह्म यद्वाक्योपक्रमे प्रक्रान्तम् ‘ प्राणो ब्रह्म कं ब्रह्म खं ब्रह्म ’ (छा. उ. ४ । १० । ४) इति , तदेवेहाभिहितम् ; प्रकृतपरिग्रहस्य न्याय्यत्वात् , ‘ आचार्यस्तु ते गतिं वक्ता ’ (छा. उ. ४ । १४ । १) इति च गतिमात्राभिधानप्रतिज्ञानात् । कथं पुनर्वाक्योपक्रमे सुखविशिष्टं ब्रह्म विज्ञायत इति , उच्यते — ‘ प्राणो ब्रह्म कं ब्रह्म खं ब्रह्म ’ (छा. उ. ४ । १० । ४) इत्येतदग्नीनां वचनं श्रुत्वोपकोसल उवाच — ‘ विजानाम्यहं यत्प्राणो ब्रह्म , कं च तु खं च न विजानामि ’ इति । तत्रेदं प्रतिवचनम् — ‘ यद्वाव कं तदेव खं यदेव खं तदेव कम् ’ इति । तत्र खं शब्दो भूताकाशे निरूढो लोके । यदि तस्य विशेषणत्वेन कंशब्दः सुखवाची नोपादीयेत , तथा सति केवले भूताकाशे ब्रह्मशब्दो नामादिष्विव प्रतीकाभिप्रायेण प्रयुक्त इति प्रतीतिः स्यात् । तथा कंशब्दस्य विषयेन्द्रियसम्पर्कजनिते सामये सुखे प्रसिद्धत्वात् , यदि तस्य खंशब्दो विशेषणत्वेन नोपादीयेत ; लौकिकं सुखं ब्रह्मेति प्रतीतिः स्यात् । इतरेतर विशेषितौ तु कंखंशब्दौ सुखात्मकं ब्रह्म गमयतः । तत्र द्वितीये ब्रह्मशब्देऽनुपादीयमाने ‘ कं खं ब्रह्म ’ इत्येवोच्यमाने कंशब्दस्य विशेषणत्वेनैवोपयुक्तत्वात्सुखस्य गुणस्याध्येयत्वं स्यात् । तन्मा भूत् — इत्युभयोः कंखंशब्दयोर्ब्रह्मशब्दशिरस्त्वम् — ‘ कं ब्रह्म खं ब्रह्म ’ इति । इष्टं हि सुखस्यापि गुणस्य गुणिवद्ध्येयत्वम् । तदेवं वाक्योपक्रमे सुखविशिष्टं ब्रह्मोपदिष्टम् । प्रत्येकं च गार्हपत्यादयोऽग्नयः स्वं स्वं महिमानमुपदिश्य ‘ एषा सोम्य तेऽस्मद्विद्यात्मविद्या च ’ इत्युपसंहरन्तः पूर्वत्र ब्रह्म निर्दिष्टमिति ज्ञापयन्ति । ‘ आचार्यस्तु ते गतिं वक्ता ’ इति च गतिमात्राभिधानप्रतिज्ञानमर्थान्तरविवक्षां वारयति । ‘ यथा पुष्करपलाश आपो न श्लिष्यन्त एवमेवंविदि पापं कर्म न श्लिष्यते ’ (छा. उ. ४ । १४ । ३) इति चाक्षिस्थानं पुरुषं विजानतः पापेनानुपघातं ब्रुवन्नक्षिस्थानस्य पुरुषस्य ब्रह्मत्वं दर्शयति । तस्मात्प्रकृतस्यैव ब्रह्मणोऽक्षिस्थानतां संयद्वामत्वादिगुणतां चोक्त्वा अर्चिरादिकां तद्विदो गतिं वक्ष्यामीत्युपक्रमते — ‘ य एषोऽक्षिणि पुरुषो दृश्यत एष आत्मेति होवाच ’ (छा. उ. ४ । १५ । १) इति ॥ १५ ॥",
    "citations": [
      {
        "href": "Chandogya?id=Ch_C04_S10_V04",
        "text": "‘ प्राणो"
      },
      {
        "href": "Chandogya?id=Ch_C04_S14_V01",
        "text": "‘ आचार्यस्तु"
      },
      {
        "href": "Chandogya?id=Ch_C04_S10_V04",
        "text": "‘ प्राणो"
      },
      {
        "href": "Chandogya?id=Ch_C04_S14_V03",
        "text": "‘ यथा"
      },
      {
        "href": "Chandogya?id=Ch_C04_S15_V01",
        "text": "‘ य"
      }
    ]
  },
  {
    "source_url": "https://advaitasharada.sringeri.net/display/bhashya/BS/devanagari",
    "source_sha256": "3e25449a44a0e912318db91030eb2e604e0c4eb2f8b5ceaa4ff4f92ae5e5bb80",
    "chapter_id": "BS_C01",
    "section_id": "BS_C01_S02",
    "verse_id": "BS_C01_S02_V15",
    "block_id": "BS_C01_S02_V15_VERSETEXT_01",
    "block_type": "versetext",
    "text": "सुखविशिष्टाभिधानादेव च ॥ १५ ॥",
    "citations": []
  },
  {
    "source_url": "https://advaitasharada.sringeri.net/display/bhashya/BS/devanagari",
    "source_sha256": "3e25449a44a0e912318db91030eb2e604e0c4eb2f8b5ceaa4ff4f92ae5e5bb80",
    "chapter_id": "BS_C01",
    "section_id": "BS_C01_S02",
    "verse_id": "BS_C01_S02_V16",
    "block_id": "BS_C01_S02_V16_B1",
    "block_type": "bhashya",
    "text": "इत श्चा क्षिस्थानः पुरुषः परमेश्वरः , यस्माच्छ्रुतोपनिषत्कस्य श्रुतरहस्यविज्ञानस्य ब्रह्मविदो या गतिर्देवयानाख्या प्रसिद्धा श्रुतौ — ‘ अ थो त्तरेण तपसा ब्रह्मचर्येण श्रद्धया विद्ययात्मानमन्विष्यादित्यमभिजयन्ते । एतद्वै प्राणानामायतनमेतदमृतमभयमेतत्परायणमेतस्मान्न पुनरावर्तन्ते ’ (प्र. उ. १ । १०) इति , स्मृतावपि — ‘ अग्निर्ज्योतिरहः शुक्लः षण्मासा उत्तरायणम् । तत्र प्रयाता गच्छन्ति ब्रह्म ब्रह्मविदो जनाः ’ (भ. गी. ८ । २४) इति , सैवेहाक्षिपुरुषविदोऽभिधीयमाना दृश्यते । ‘ अथ यदु चैवास्मिञ्छव्यं कुर्वन्ति यदि च नार्चिषमेवाभिसम्भवन्ति ’ इत्युपक्रम्य ‘ आदित्याच्चन्द्रमसं चन्द्रमसो विद्युतं तत्पुरुषोऽमानवः स एनान्ब्रह्म गमयत्येष देवपथो ब्रह्मपथ एतेन प्रतिपद्यमाना इमं मानवमावर्तं नावर्तन्ते ’ (छा. उ. ४ । १५ । ५) इति । तदिह ब्रह्मविद्विषयया प्रसिद्धया गत्या अक्षिस्थानस्य ब्रह्मत्वं निश्चीयते ॥ १६ ॥",
    "citations": [
      {
        "href": "Prashna?id=PR_C01_V10",
        "text": "‘ अ"
      },
      {
        "href": "Gita?id=BG_C08_V24",
        "text": "‘ अग्निर्ज्योतिरहः"
      },
      {
        "href": "Chandogya?id=Ch_C04_S15_V05",
        "text": "‘ आदित्याच्चन्द्रमसं"
      }
    ]
  },
  {
    "source_url": "https://advaitasharada.sringeri.net/display/bhashya/BS/devanagari",
    "source_sha256": "3e25449a44a0e912318db91030eb2e604e0c4eb2f8b5ceaa4ff4f92ae5e5bb80",
    "chapter_id": "BS_C01",
    "section_id": "BS_C01_S02",
    "verse_id": "BS_C01_S02_V16",
    "block_id": "BS_C01_S02_V16_VERSETEXT_01",
    "block_type": "versetext",
    "text": "श्रुतोपनिषत्कगत्यभिधानाच्च ॥ १६ ॥",
    "citations": []
  },
  {
    "source_url": "https://advaitasharada.sringeri.net/display/bhashya/BS/devanagari",
    "source_sha256": "3e25449a44a0e912318db91030eb2e604e0c4eb2f8b5ceaa4ff4f92ae5e5bb80",
    "chapter_id": "BS_C01",
    "section_id": "BS_C01_S02",
    "verse_id": "BS_C01_S02_V17",
    "block_id": "BS_C01_S02_V17_B1",
    "block_type": "bhashya",
    "text": "यत्पुनरुक्तं छायात्मा , विज्ञानात्मा , देवतात्मा वा स्यादक्षिस्थान इति , अत्रोच्यते — न च्छायात्मादिरितर इह ग्रहणमर्हति । कस्मात् ? अनवस्थितेः । न तावच्छायात्मनश्चक्षुषि नित्यमवस्थानं सम्भवति । यदैव हि कश्चित्पुरुष श्चक्षुरासीदति , तदा चक्षुषि पुरुषच्छाया दृश्यते । अपगते तस्मिन्न दृश्यते । ‘ य एषो ऽक्षिणि पुरुषः ’ इति च श्रुतिः सन्निधानात्स्वचक्षुषि दृश्यमानं पुरुषमुपास्यत्वेनोपदिशति । न चो पासनाकाले च्छायाकरं कञ्चित्पुरुषं चक्षुःसमीपे सन्निधाप्योपास्त इति युक्तं कल्पयितुम् । ‘ अ स्यै व शरीरस्य नाशमन्वेष नश्यति ’ (छा. उ. ८ । ९ । १) इति श्रुतिश्छायात्मनोऽप्यनवस्थितत्वं दर्शयति । असम्भवाच्च तस्मिन्नमृतत्वादीनां गुणानां न च्छायात्मनि प्रतीतिः । तथा विज्ञानात्मनोऽपि साधारणे कृत्स्नशरीरेन्द्रियसम्बन्धे सति न चक्षुष्येवावस्थितत्वं शक्यं वक्तुम् । ब्रह्मणस्तु सर्वव्यापिनोऽपि दृष्ट उपलब्ध्यर्थो हृदयादिदेशविशेषसम्बन्धः । समानश्च विज्ञानात्मन्यप्यमृतत्वादीनां गुणानामसम्भवः । यद्यपि विज्ञानात्मा परमात्मनोऽनन्य एव , तथाप्यविद्याकामकर्मकृतं तस्मिन्मर्त्यत्वमध्यारोपितं भयं चेत्यमृतत्वाभयत्वे नोपपद्येते । संयद्वामत्वादयश्चैतस्मिन्ननैश्वर्यादनुपपन्ना एव । देवतात्मनस्तु ‘ रश्मिभिरेषोऽस्मिन्प्रतिष्ठितः ’ इति श्रुतेः यद्यपि चक्षुष्यवस्थानं स्यात् , तथाप्यात्मत्वं तावन्न सम्भवति , पराग्रूपत्वात् । अमृतत्वादयोऽपि न सम्भवन्ति , उत्पत्तिप्रलयश्रवणात् । अमरत्वमपि देवानां चिरकालावस्थानापेक्षम् । ऐश्वर्यमपि परमेश्वरायत्तम् , न स्वाभाविकम् ; ‘ भीषास्माद्वातः पवते । भीषोदेति सूर्यः । भीषास्मादग्निश्चेन्द्रश्च । मृत्युर्धावति पञ्चमः ’ (तै. उ. २ । ८ । १) इति मन्त्रवर्णात् । तस्मात्परमेश्वर एवायमक्षिस्थानः प्रत्येतव्यः । अस्मिं श्च पक्षे ‘ दृश्यते ’ इति प्रसिद्धवदुपादानं शास्त्राद्यपेक्षं विद्वद्विषयं प्ररोचनार्थमिति व्याख्येयम् ॥ १७ ॥",
    "citations": [
      {
        "href": "Chandogya?id=Ch_C08_S09_V01",
        "text": "‘ अ"
      },
      {
        "href": "Taitiriya?id=T_C02_S08_V01",
        "text": "‘ भीषास्माद्वातः"
      }
    ]
  },
  {
    "source_url": "https://advaitasharada.sringeri.net/display/bhashya/BS/devanagari",
    "source_sha256": "3e25449a44a0e912318db91030eb2e604e0c4eb2f8b5ceaa4ff4f92ae5e5bb80",
    "chapter_id": "BS_C01",
    "section_id": "BS_C01_S02",
    "verse_id": "BS_C01_S02_V17",
    "block_id": "BS_C01_S02_V17_VERSETEXT_01",
    "block_type": "versetext",
    "text": "अनवस्थितेरसम्भवाच्च नेतरः ॥ १७ ॥",
    "citations": []
  },
  {
    "source_url": "https://advaitasharada.sringeri.net/display/bhashya/BS/devanagari",
    "source_sha256": "3e25449a44a0e912318db91030eb2e604e0c4eb2f8b5ceaa4ff4f92ae5e5bb80",
    "chapter_id": "BS_C01",
    "section_id": "BS_C01_S02",
    "verse_id": "BS_C01_S02_V18",
    "block_id": "BS_C01_S02_V18_B1",
    "block_type": "bhashya",
    "text": "‘ य इमं च लोकं परं च लोकं सर्वाणि च भूतानि योऽन्तरो यमयति ’ (बृ. उ. ३ । ७ । १) इत्युपक्रम्य श्रूयते — ‘ यः पृथिव्यां तिष्ठन्पृथिव्या अन्तरो यं पृथिवी न वेद यस्य पृथिवी शरीरं यः पृथिवीमन्तरो यमयत्येष त आत्मान्तर्याम्यमृतः ’ (बृ. उ. ३ । ७ । ३) इत्यादि । अ त्रा धिदैवतमधिलोकमधिवेदमधियज्ञमधिभूतमध्यात्मं च कश्चिदन्तरवस्थितो यमयिता अन्तर्यामीति श्रूयते । स किमधिदैवाद्यभिमानी देवतात्मा कश्चित् , किं वा प्राप्ताणिमाद्यैश्वर्यः कश्चिद्योगी , किं वा परमात्मा , किं वार्थान्तरं किञ्चित् , इत्यपूर्वसंज्ञादर्शनात्संशयः । किं तावन्नः प्रतिभाति ? संज्ञाया अप्रसिद्धत्वात्संज्ञिनाप्यप्रसिद्धेनार्थान्तरेण केनचिद्भवितव्यमिति । अथवा नानिरूपितरूपमर्थान्तरं शक्यमस्त्यभ्युपगन्तुम् । अन्तर्यामिशब्दश्चान्तर्यमनयोगेन प्रवृत्तो नात्यन्तमप्रसिद्धः । तस्मात्पृथिव्याद्यभिमानी कश्चिद्देवोऽन्तर्यामी स्यात् । तथा च श्रूयते — ‘ पृथिव्येव यस्यायतनमग्निर्लोको मनो ज्योतिः ’ (बृ. उ. ३ । ९ । १०) इत्यादि । स च कार्यकरणवत्त्वात्पृथिव्यादीनन्तस्तिष्ठन्यमयतीति युक्तं देवतात्मनो यमयितृत्वम् । योगिनो वा कस्यचित्सिद्धस्य सर्वानुप्रवेशेन यमयितृत्वं स्यात् । न तु परमात्मा प्रतीयेत , अकार्यकरणत्वात् — इ त्येवं प्राप्ते इदमुच्यते —",
    "citations": [
      {
        "href": "Brha?id=BR_C03_S07_V01",
        "text": "‘ य"
      },
      {
        "href": "Brha?id=BR_C03_S07_V03",
        "text": "‘ यः"
      },
      {
        "href": "Brha?id=BR_C03_S09_V10",
        "text": "‘ पृथिव्येव"
      }
    ]
  },
  {
    "source_url": "https://advaitasharada.sringeri.net/display/bhashya/BS/devanagari",
    "source_sha256": "3e25449a44a0e912318db91030eb2e604e0c4eb2f8b5ceaa4ff4f92ae5e5bb80",
    "chapter_id": "BS_C01",
    "section_id": "BS_C01_S02",
    "verse_id": "BS_C01_S02_V18",
    "block_id": "BS_C01_S02_V18_B2",
    "block_type": "bhashya",
    "text": "योऽन्तर्याम्यधिदैवादिषु श्रूयते , स परमात्मैव स्यात् , नान्य इति । कुतः ? तद्धर्मव्यपदेशात् । तस्य हि परमात्मनो धर्मा इह निर्दिश्यमाना दृश्यन्ते । पृथिव्यादि तावदधिदैवादिभेदभिन्नं समस्तं विकारजातमन्तस्तिष्ठन्यमयतीति परमात्मनो यमयितृत्वं धर्म उपपद्यते । सर्वविकारकारणत्वे सति सर्वशक्त्युपपत्तेः । ‘ एष त आत्मान्तर्याम्यमृतः ’ इति चात्मत्वामृतत्वे मुख्ये परमात्मन उपपद्येते । ‘ यं पृथिवी न वेद ’ इति च पृथिवीदेवताया अविज्ञेयमन्तर्यामिणं ब्रुवन्देवतात्मनोऽन्यमन्तर्यामिणं दर्शयति । पृथिवी देवता ह्यहमस्मि पृथिवीत्यात्मानं विजानीयात् । तथा ‘ अदृष्टोऽश्रुतः ’ इत्यादिव्यपदेशो रूपादिविहीनत्वात्परमात्मन उपपद्यत इति । यत्त्वकार्यकरणस्य परमात्मनो यमयितृत्वं नोपपद्यत इति , नैष दोषः ; यान्नियच्छति तत्कार्यकरणैरेव तस्य कार्यकरणवत्त्वोपपत्तेः । तस्या प्य न्यो नियन्तेत्यनवस्थादोषश्च न सम्भवति , भेदाभावात् । भेदे हि सत्यनवस्थादोषोपपत्तिः । तस्मात्परमात्मैवान्तर्यामी ॥ १८ ॥",
    "citations": []
  },
  {
    "source_url": "https://advaitasharada.sringeri.net/display/bhashya/BS/devanagari",
    "source_sha256": "3e25449a44a0e912318db91030eb2e604e0c4eb2f8b5ceaa4ff4f92ae5e5bb80",
    "chapter_id": "BS_C01",
    "section_id": "BS_C01_S02",
    "verse_id": "BS_C01_S02_V18",
    "block_id": "BS_C01_S02_V18_VERSETEXT_01",
    "block_type": "versetext",
    "text": "अन्तर्याम्यधिदैवादिषु तद्धर्मव्यपदेशात् ॥ १८ ॥",
    "citations": []
  },
  {
    "source_url": "https://advaitasharada.sringeri.net/display/bhashya/BS/devanagari",
    "source_sha256": "3e25449a44a0e912318db91030eb2e604e0c4eb2f8b5ceaa4ff4f92ae5e5bb80",
    "chapter_id": "BS_C01",
    "section_id": "BS_C01_S02",
    "verse_id": "BS_C01_S02_V19",
    "block_id": "BS_C01_S02_V19_B1",
    "block_type": "bhashya",
    "text": "स्यादेतत् — अदृष्टत्वादयो धर्माः साङ्ख्यस्मृतिकल्पितस्य प्रधानस्याप्युपपद्यन्ते , रूपादिहीनतया तस्य तैरभ्युपगमात् । ‘ अप्रतर्क्य म विज्ञेयं प्रसुप्तमिव सर्वतः ’ (मनु. १ । ५) इति हि स्मरन्ति । तस्यापि नियन्तृत्वं सर्वविकारकारणत्वादुपपद्यते । तस्मात्प्रधानमन्तर्यामिशब्दं स्यात् । ‘ ईक्षतेर्नाशब्दम् ’ (ब्र. सू. १ । १ । ५) इत्यत्र निराकृतमपि सत् प्रधानमिहादृष्टत्वादिव्यपदेशसम्भवेन पुनराशङ्क्यते । अत उत्तरमुच्यते — न च स्मार्तं प्रधानमन्तर्यामिशब्दं भवितुमर्हति । कस्मात् ? अतद्धर्माभिलापात् । यद्यप्यदृष्टत्वादिव्यपदेशः प्रधानस्य सम्भवति , तथापि न द्रष्टृत्वादिव्यपदेशः सम्भवति , प्रधानस्याचेतनत्वेन तैरभ्युपगमात् । ‘ अदृष्टो द्रष्टाश्रुतः श्रोतामतो मन्ताविज्ञातो विज्ञाता ’ (बृ. उ. ३ । ७ । २३) इति हि वाक्यशेष इह भवति । आत्मत्वमपि न प्रधानस्योपपद्यते ॥ १९ ॥",
    "citations": [
      {
        "href": "",
        "text": "‘ अप्रतर्क्य"
      },
      {
        "href": "BS?id=BS_C01_S01_V05",
        "text": "‘ ईक्षतेर्नाशब्दम्"
      },
      {
        "href": "Brha?id=BR_C03_S07_V23",
        "text": "‘ अदृष्टो"
      }
    ]
  },
  {
    "source_url": "https://advaitasharada.sringeri.net/display/bhashya/BS/devanagari",
    "source_sha256": "3e25449a44a0e912318db91030eb2e604e0c4eb2f8b5ceaa4ff4f92ae5e5bb80",
    "chapter_id": "BS_C01",
    "section_id": "BS_C01_S02",
    "verse_id": "BS_C01_S02_V19",
    "block_id": "BS_C01_S02_V19_VERSETEXT_01",
    "block_type": "versetext",
    "text": "न च स्मार्तमतद्धर्माभिलापात् ॥ १९ ॥",
    "citations": []
  },
  {
    "source_url": "https://advaitasharada.sringeri.net/display/bhashya/BS/devanagari",
    "source_sha256": "3e25449a44a0e912318db91030eb2e604e0c4eb2f8b5ceaa4ff4f92ae5e5bb80",
    "chapter_id": "BS_C01",
    "section_id": "BS_C01_S02",
    "verse_id": "BS_C01_S02_V20",
    "block_id": "BS_C01_S02_V20_B1",
    "block_type": "bhashya",
    "text": "नेति पूर्वसूत्रादनुवर्तते । शारीरश्च नान्तर्यामी स्यात् । कस्मात् ? यद्यपि द्रष्टृत्वादयो धर्मास्तस्य सम्भवन्ति , तथापि घटाकाशवदुपाधिपरिच्छिन्नत्वान्न कार्त्स्न्येन पृथिव्यादिष्वन्तरवस्थातुं नियन्तुं च शक्नोति । अपि चोभयेऽपि हि शाखिनः काण्वा माध्यन्दिनाश्चान्तर्यामिणो भेदेनैनं शारीरं पृथिव्यादिवदधिष्ठानत्वेन नियम्यत्वेन चाधीयते — ‘ यो विज्ञाने तिष्ठन् ’ (बृ. उ. ३ । ७ । २२) इति काण्वाः । ‘ य आत्मनि तिष्ठन् ’ इति माध्यन्दिनाः । ‘ य आत्मनि तिष्ठन् ’ इत्यस्मिंस्तावत् पाठे भवत्यात्मशब्दः शारीरस्य वाचकः । ‘ यो विज्ञाने तिष्ठन् ’ इत्यस्मिन्नपि पाठे विज्ञानशब्देन शारीर उच्यते , विज्ञानमयो हि शारीर इति । तस्माच्छारीरादन्य ईश्वरोऽन्तर्यामीति सिद्धम् । कथं पुनरेकस्मिन्देहे द्वौ द्रष्टारावुपपद्येते यश्चायमीश्वरोऽन्तर्यामी , यश्चायमितरः शारीरः ? का पुन रि हानुपपत्तिः ? ‘ नान्यो ऽतोऽस्ति द्रष्टा ’ इत्यादिश्रुतिवचनं विरुध्येत । अत्र हि प्रकृतादन्तर्यामिणोऽन्यं द्रष्टारं श्रोतारं मन्तारं विज्ञातारं चात्मानं प्रतिषेधति । नियन्त्रन्तर प्रतिषेधार्थमेतद्वचनमिति चेत् , न ; नियन्त्रन्तराप्रसङ्गा दविशेष श्रवणाच्च । अत्रोच्यते — अविद्याप्रत्युपस्थापितकार्यकरणोपाधिनिमित्तोऽयं शारीरान्तर्यामिणोर्भेदव्यपदेशः , न पारमार्थिकः । एको हि प्रत्यगात्मा भवति , न द्वौ प्रत्यगात्मानौ सम्भवतः । एकस्यैव तु भेदव्यवहार उपाधिकृतः , यथा घटाकाशो महाकाश इति । ततश्च ज्ञातृज्ञेयादिभेदश्रुतयः प्रत्यक्षादीनि च प्रमाणानि संसारानुभवो विधिप्रतिषेधशास्त्रं चेति सर्वमेतदुपपद्यते । तथा च श्रुतिः — ‘ यत्र हि द्वैतमिव भवति तदितर इतरं पश्यति ’ इत्यविद्याविषये सर्वं व्यवहारं दर्शयति । ‘ यत्र त्वस्य सर्वमात्मैवाभूत्तत्केन कं पश्येत् ’ इति विद्याविषये सर्वं व्यवहारं वारयति ॥ २० ॥",
    "citations": [
      {
        "href": "Brha?id=BR_C03_S07_V22",
        "text": "‘ यो"
      }
    ]
  },
  {
    "source_url": "https://advaitasharada.sringeri.net/display/bhashya/BS/devanagari",
    "source_sha256": "3e25449a44a0e912318db91030eb2e604e0c4eb2f8b5ceaa4ff4f92ae5e5bb80",
    "chapter_id": "BS_C01",
    "section_id": "BS_C01_S02",
    "verse_id": "BS_C01_S02_V20",
    "block_id": "BS_C01_S02_V20_I01",
    "block_type": "leading_bhashya",
    "text": "यदि प्रधान मा त्मत्वद्रष्टृत्वाद्यसम्भवान्नान्तर्याम्यभ्युपगम्यते , शारीरस्तर्ह्यन्तर्यामी भवतु । शारीरो हि चेतनत्वाद्द्रष्टा श्रोता मन्ता विज्ञाता च भवति , आत्मा च प्रत्यक्त्वात् । अमृतश्च , धर्माधर्मफलोपभोगोपपत्तेः । अदृष्टत्वादयश्च धर्माः शारीरे प्रसिद्धाः । दर्शनादिक्रियायाः कर्तरि प्रवृत्तिविरोधात् । ‘ न दृष्टेर्द्रष्टारं पश्येः ’ (बृ. उ. ३ । ४ । २) इत्यादिश्रुतिभ्यश्च । तस्य च कार्यकरणसङ्घातमन्तर्यमयितुं शीलम् , भोक्तृत्वात् । तस्माच्छारीरोऽन्तर्यामीत्यत उत्तरं पठति —",
    "citations": [
      {
        "href": "Brha?id=BR_C03_S04_V02",
        "text": "‘ न"
      }
    ]
  },
  {
    "source_url": "https://advaitasharada.sringeri.net/display/bhashya/BS/devanagari",
    "source_sha256": "3e25449a44a0e912318db91030eb2e604e0c4eb2f8b5ceaa4ff4f92ae5e5bb80",
    "chapter_id": "BS_C01",
    "section_id": "BS_C01_S02",
    "verse_id": "BS_C01_S02_V20",
    "block_id": "BS_C01_S02_V20_VERSETEXT_01",
    "block_type": "versetext",
    "text": "शारीरश्चोभयेऽपि हि भेदेनैनमधीयते ॥ २० ॥",
    "citations": []
  },
  {
    "source_url": "https://advaitasharada.sringeri.net/display/bhashya/BS/devanagari",
    "source_sha256": "3e25449a44a0e912318db91030eb2e604e0c4eb2f8b5ceaa4ff4f92ae5e5bb80",
    "chapter_id": "BS_C01",
    "section_id": "BS_C01_S02",
    "verse_id": "BS_C01_S02_V21",
    "block_id": "BS_C01_S02_V21_B1",
    "block_type": "bhashya",
    "text": "‘ अथ परा यया तदक्षरमधिगम्यते ’(मु. उ. १ । १ । ५) , ‘ यत्त द द्रेश्यमग्राह्यमगोत्रमवर्णमचक्षुःश्रोत्रं तदपाणिपादम् , नित्यं विभुं सर्वगतं सुसूक्ष्मं तदव्ययं यद्भूतयोनिं परिपश्यन्ति धीराः ’ (मु. उ. १ । १ । ६) इति श्रूयते । तत्र संशयः — किमयमदृश्यत्वादिगुणको भूतयोनिः प्रधानं स्यात् , उत शारीरः , आहोस्वित्परमेश्वर इति । तत्र प्रधानमचेतनं भूतयोनिरिति युक्तम् , अचेतनानामेव तस्य दृष्टान्तत्वेनोपादानात् । ‘ यथोर्णनाभिः सृजते गृह्णते च यथा पृथिव्यामोषधयः सम्भवन्ति । यथा सतः पुरुषात्केशलोमानि तथाक्षरात्सम्भवतीह विश्वम् ’ (मु. उ. १ । १ । ७) इति । ननूर्णनाभिः पुरुषश्च चेतनाविह दृष्टान्तत्वेनोपात्तौ ; नेति ब्रूमः । न हि केवलस्य चेतनस्य तत्र सूत्रयोनित्वं केशलोमयोनित्वं चास्ति । चेतनाधिष्ठितं ह्यचेतनमूर्णनाभिशरीरं सूत्रस्य योनिः , पुरुषशरीरं च केशलोम्नामिति प्रसिद्धम् । अपि च पूर्वत्रादृष्टत्वाद्यभिलापसम्भवेऽपि द्रष्टृत्वाद्यभिलापासम्भवान्न प्रधानमभ्युपगतम् । इह त्वदृश्यत्वादयो धर्माः प्रधाने सम्भवन्ति । न चात्र विरुध्यमानो धर्मः कश्चिदभिलप्यते । ननु ‘ यः सर्वज्ञः सर्ववित् ’ (मु. उ. १ । १ । ९) इत्ययं वाक्यशेषोऽचेतने प्रधाने न सम्भवति , कथं प्रधानं भूतयोनिः प्रतिज्ञायत इति ; अत्रोच्यते — ‘ यया तदक्षरमधिगम्यते ’ ‘ यत्तदद्रेश्यम् ’ इत्यक्षरशब्देनादृश्यत्वादिगुणकं भूतयोनिं श्रावयित्वा , पुनरन्ते श्रावयिष्यति — ‘ अक्षरात्परतः परः ’ (मु. उ. २ । १ । २) इति । तत्र यः परोऽक्षराच्छ्रुतः , स सर्वज्ञः सर्ववित्सम्भविष्यति । प्रधानमेव त्वक्षरशब्दनिर्दिष्टं भूतयोनिः । यदा तु योनिशब्दो निमित्तवाची , तदा शारीरोऽपि भूतयोनिः स्यात् , धर्माधर्माभ्यां भूतजातस्योपार्जनादिति । एवं प्राप्ते अभिधीयते —",
    "citations": [
      {
        "href": "Mundaka?id=MD_C01_S01_V05",
        "text": "‘ अथ"
      },
      {
        "href": "Mundaka?id=MD_C01_S01_V06",
        "text": "‘ यत्त"
      },
      {
        "href": "Mundaka?id=MD_C01_S01_V07",
        "text": "‘ यथोर्णनाभिः"
      },
      {
        "href": "Mundaka?id=MD_C01_S01_V09",
        "text": "‘ यः"
      },
      {
        "href": "Mundaka?id=MD_C02_S01_V02",
        "text": "‘ अक्षरात्परतः"
      }
    ]
  },
  {
    "source_url": "https://advaitasharada.sringeri.net/display/bhashya/BS/devanagari",
    "source_sha256": "3e25449a44a0e912318db91030eb2e604e0c4eb2f8b5ceaa4ff4f92ae5e5bb80",
    "chapter_id": "BS_C01",
    "section_id": "BS_C01_S02",
    "verse_id": "BS_C01_S02_V21",
    "block_id": "BS_C01_S02_V21_B2",
    "block_type": "bhashya",
    "text": "योऽयमदृश्यत्वादिगुणको भूतयोनिः , स परमेश्वर एव स्यात् , नान्य इति । कथमेतदवगम्यते ? धर्मोक्तेः । परमेश्वरस्य हि धर्म इहोच्यमानो दृश्यते — ‘ यः सर्वज्ञः सर्ववित् ’ इति । न हि प्रधानस्याचेतनस्य शारीरस्य वोपाधिपरिच्छिन्नदृष्टेः सर्वज्ञत्वं सर्ववित्त्वं वा सम्भवति । न न्व क्षरशब्दनिर्दिष्टाद्भूतयोनेः परस्यैव तत्सर्वज्ञत्वं सर्ववित्त्वं च , न भूतयोनिविषयमित्युक्तम् ; अत्रोच्यते — नैवं सम्भवति ; यत्कारणम् ‘ अक्षरात्सम्भवतीह विश्वम् ’ इति प्रकृतं भूतयोनिमिह जायमानप्रकृतित्वेन निर्दिश्य , अनन्तरमपि जायमानप्रकृतित्वेनैव सर्वज्ञं निर्दिशति — ‘ यः सर्वज्ञः सर्वविद्यस्य ज्ञानमयं तपः । तस्मादेतद्ब्रह्म नाम रूपमन्नं च जायते ’ इति । तस्मान्निर्देशसाम्येन प्रत्यभिज्ञायमानत्वात्प्रकृतस्यैवाक्षरस्य भूतयोनेः सर्वज्ञत्वं सर्ववित्त्वं च धर्म उच्यत इति गम्यते । ‘ अक्षरात्परतः परः ’ इत्यत्रापि न प्रकृताद्भूतयोनेरक्षरात्परः कश्चिदभिधीयते । कथमेतदवगम्यते ? ‘ ये ना क्षरं पुरुषं वेद सत्यं प्रोवाच तां तत्त्वतो ब्रह्मविद्याम् ’ (मु. उ. १ । २ । १३) इति प्रकृतस्यैवाक्षरस्य भूतयोनेरदृश्यत्वादिगुणकस्य वक्तव्यत्वेन प्रतिज्ञातत्वात् । कथं तर्हि ‘ अक्षरात्परतः परः ’ इति व्यपदिश्यत इति ? उत्तरसूत्रे तद्वक्ष्यामः । अपि चा त्र द्वे विद्ये वेदितव्ये उक्ते — ‘ परा चैवापरा च ’ इति । तत्रापरामृग्वेदादिलक्षणां विद्यामुक्त्वा ब्रवीति ‘ अथ परा यया तदक्षरमधिगम्यते ’ इत्यादि । तत्र परस्या विद्याया विषयत्वेनाक्षरं श्रुतम् । यदि पुनः परमेश्वरादन्यददृश्यत्वादिगुणकमक्षरं परिकल्प्येत , नेयं परा विद्या स्यात् । परापरविभागो ह्य यं विद्ययोः अभ्युदयनिःश्रेयसफलतया परिकल्प्यते । न च प्रधानविद्या निःश्रेयसफला केनचिदभ्युपगम्यते । तिस्रश्च विद्याः प्रतिज्ञायेरन् , त्वत्पक्षेऽक्षराद्भूतयोनेः परस्य परमात्मनः प्रतिपाद्यमानत्वात् । द्वे एव तु विद्ये वेदितव्ये इह निर्दिष्टे । ‘ कस्मि न्नु भगवो विज्ञाते सर्वमिदं विज्ञातं भवति ’ (मु. उ. १ । १ । ३) इति चैकविज्ञानेन सर्वविज्ञानापेक्षणं सर्वात्मके ब्रह्मणि विवक्ष्यमाणेऽवकल्पते , नाचेतनमात्रैकायतने प्रधाने , भोग्यव्यतिरिक्ते वा भोक्तरि । अपि च ‘ स ब्रह्मविद्यां सर्वविद्याप्रतिष्ठामथर्वाय ज्येष्ठपुत्राय प्राह ’ (मु. उ. १ । १ । १) इति ब्रह्मविद्यां प्राधान्येनोपक्रम्य परापरविभागेन परां विद्यामक्षराधिगमनीं दर्शयन् तस्या ब्रह्मविद्यात्वं दर्शयति । सा च ब्रह्मविद्यासमाख्या तदधिगम्यस्य अक्षरस्याब्रह्मत्वे बाधिता स्यात् । अपरा ऋग्वेदादिलक्षणा कर्मविद्या ब्रह्मविद्योपक्रमे उपन्यस्यते ब्रह्मविद्याप्रशंसायै — ‘ प्लवा ह्येते अदृढा यज्ञरूपा अष्टादशोक्तमवरं येषु कर्म । एतच्छ्रेयो येऽभिनन्दन्ति मूढा जरामृत्युं ते पुनरेवापि यन्ति ’ (मु. उ. १ । २ । ७) इत्येवमादिनिन्दावचनात् । निन्दित्वा चापरां विद्यां ततो विरक्तस्य परविद्याधिकारं दर्शयति — ‘ परीक्ष्य लोकान्कर्मचितान्ब्राह्मणो निर्वेदमायान्नास्त्यकृतः कृतेन । तद्विज्ञानार्थं स गुरुमेवाभिगच्छेत्समित्पाणिः श्रोत्रियं ब्रह्मनिष्ठम् ’ (मु. उ. १ । २ । १२) इति । यत्तूक्तम् — अचेतनानां पृथिव्यादीनां दृष्टान्तत्वेनोपादानाद्दार्ष्टान्तिकेनाप्यचेतनेनैव भूतयोनिना भवितव्यमिति , तदयुक्तम् ; न हि दृष्टान्तदार्ष्टान्तिकयोरत्यन्तसाम्येन भवितव्यमिति नियमोऽस्ति । अपि च स्थूलाः पृथिव्यादयो दृष्टान्तत्वेनोपात्ता इति न स्थूल एव दार्ष्टान्तिको भूतयोनिरभ्युपगम्यते । तस्माददृश्यत्वादिगुणको भूतयोनिः परमेश्वर एव ॥ २१ ॥",
    "citations": [
      {
        "href": "Mundaka?id=MD_C01_S02_V13",
        "text": "‘ ये"
      },
      {
        "href": "Mundaka?id=MD_C01_S01_V03",
        "text": "‘ कस्मि"
      },
      {
        "href": "Mundaka?id=MD_C01_S01_V01",
        "text": "‘ स"
      },
      {
        "href": "Mundaka?id=MD_C01_S02_V07",
        "text": "‘ प्लवा"
      },
      {
        "href": "Mundaka?id=MD_C01_S02_V12",
        "text": "‘ परीक्ष्य"
      }
    ]
  },
  {
    "source_url": "https://advaitasharada.sringeri.net/display/bhashya/BS/devanagari",
    "source_sha256": "3e25449a44a0e912318db91030eb2e604e0c4eb2f8b5ceaa4ff4f92ae5e5bb80",
    "chapter_id": "BS_C01",
    "section_id": "BS_C01_S02",
    "verse_id": "BS_C01_S02_V21",
    "block_id": "BS_C01_S02_V21_VERSETEXT_01",
    "block_type": "versetext",
    "text": "अदृश्यत्वादिगुणको धर्मोक्तेः ॥ २१ ॥",
    "citations": []
  },
  {
    "source_url": "https://advaitasharada.sringeri.net/display/bhashya/BS/devanagari",
    "source_sha256": "3e25449a44a0e912318db91030eb2e604e0c4eb2f8b5ceaa4ff4f92ae5e5bb80",
    "chapter_id": "BS_C01",
    "section_id": "BS_C01_S02",
    "verse_id": "BS_C01_S02_V22",
    "block_id": "BS_C01_S02_V22_B1",
    "block_type": "bhashya",
    "text": "इतश्च परमेश्वर एव भूतयोनिः , नेतरौ — शारीरः प्रधानं वा । कस्मात् ? विशेषणभेदव्यपदेशाभ्याम् । विशिनष्टि हि प्रकृतं भूतयोनिं शारीराद्विलक्षणत्वेन — ‘ दिव्यो ह्यमूर्तः पुरुषः सबाह्याभ्यन्तरो ह्यजः । अप्राणो ह्यमनाः शुभ्रः ’ (मु. उ. २ । १ । २) इति । न ह्येतद्दिव्यत्वादिविशेषणम् अविद्याप्रत्युपस्थापितनामरूपपरिच्छेदाभिमानिनः तद्धर्मान्स्वात्मनि कल्पयतः शारीरस्योपपद्यते । तस्मात्साक्षादौपनिषदः पुरुष इहोच्यते । तथा प्रधानादपि प्रकृतं भूतयोनिं भेदेन व्यपदिशति — ‘ अक्षरात्परतः परः ’ इति । अक्षरमव्याकृतं नामरूपबीजशक्तिरूपं भूतसूक्ष्ममीश्वराश्रयं तस्यैवोपाधिभूतम् , सर्वस्माद्विकारात्परो यो ऽविकारः , तस्मात्परतः परः इति भेदेन व्यपदिशन् परमात्मानमिह विवक्षितं दर्शयति । नात्र प्रधानं नाम किञ्चित्स्वतन्त्रं तत्त्वमभ्युपगम्य , तस्माद्भेदव्यपदेश उच्यते । किं तर्हि ? यदि प्रधानमपि कल्प्यमानं श्रुत्यविरोधेनाव्याकृतादिशब्दवाच्यं भूतसूक्ष्मं परिकल्प्येत , परिकल्प्यताम् । तस्माद्भेदव्यपदेशात् परमेश्वरो भूतयोनिरित्येतदिह प्रतिपाद्यते ॥ २२ ॥",
    "citations": [
      {
        "href": "Mundaka?id=MD_C02_S01_V02",
        "text": "‘ दिव्यो"
      }
    ]
  },
  {
    "source_url": "https://advaitasharada.sringeri.net/display/bhashya/BS/devanagari",
    "source_sha256": "3e25449a44a0e912318db91030eb2e604e0c4eb2f8b5ceaa4ff4f92ae5e5bb80",
    "chapter_id": "BS_C01",
    "section_id": "BS_C01_S02",
    "verse_id": "BS_C01_S02_V22",
    "block_id": "BS_C01_S02_V22_VERSETEXT_01",
    "block_type": "versetext",
    "text": "विशेषणभेदव्यपदेशाभ्यां च नेतरौ ॥ २२ ॥",
    "citations": []
  },
  {
    "source_url": "https://advaitasharada.sringeri.net/display/bhashya/BS/devanagari",
    "source_sha256": "3e25449a44a0e912318db91030eb2e604e0c4eb2f8b5ceaa4ff4f92ae5e5bb80",
    "chapter_id": "BS_C01",
    "section_id": "BS_C01_S02",
    "verse_id": "BS_C01_S02_V23",
    "block_id": "BS_C01_S02_V23_B1",
    "block_type": "bhashya",
    "text": "अपि च ‘ अक्षरात्परतः परः ’ इत्यस्यानन्तरम् ‘ एतस्माज्जायते प्राणः ’ इति प्राणप्रभृतीनां पृथिवीपर्यन्तानां तत्त्वानां सर्गमुक्त्वा , तस्यैव भूतयोनेः सर्वविकारात्मकं रूपमुपन्यस्यमानं पश्यामः — ‘ अग्निर्मूर्धा चक्षुषी चन्द्रसूर्यौ दिशः श्रोत्रे वाग्विवृताश्च वेदाः । वायुः प्राणो हृदयं विश्वमस्य पद्भ्यां पृथिवी ह्येष सर्वभूतान्तरात्मा ’ (मु. उ. २ । १ । ४) इति । तच्च परमेश्वरस्यैवोचितम् , सर्वविकारकारणत्वात् । न शारीरस्य तनुमहिम्नः ; नापि प्रधानस्य अयं रूपोपन्यासः सम्भवति , सर्वभूतान्तरात्मत्वासम्भवात् । तस्मात्परमेश्वर एव भूतयोनिः , नेतराविति गम्यते । कथं पुनर्भूतयोनेरयं रूपोपन्यास इति गम्यते ? प्रकरणात् , ‘ एषः ’ इति च प्रकृतानुकर्षणात् । भूतयोनिं हि प्रकृत्य ‘ एतस्माज्जायते प्राणः ’ ‘ एष सर्वभूतान्तरात्मा ’ इति वचनं भूतयोनिविषयमेव भवति । यथा उपाध्यायं प्रकृत्य ‘ एतस्मादधीष्व , एष वेदवेदाङ्गपारगः ’ इति वचनमुपाध्यायविषयं भवति , तद्वत् । कथं पुनरदृश्यत्वादिगुणकस्य भूतयोनेर्विग्रहवद्रूपं सम्भवति ? सर्वात्मत्वविवक्षयेदमुच्यते , न तु विग्रहवत्त्वविवक्षया इत्यदोषः , ‘ अहमन्नम् ’ ‘ अहमन्नादः ’ (तै. उ. ३ । १० । ६) इत्यादिवत् ॥",
    "citations": [
      {
        "href": "Mundaka?id=MD_C02_S01_V04",
        "text": "‘ अग्निर्मूर्धा"
      },
      {
        "href": "Taitiriya?id=T_C03_S10_V06",
        "text": "‘ अहमन्नादः"
      }
    ]
  },
  {
    "source_url": "https://advaitasharada.sringeri.net/display/bhashya/BS/devanagari",
    "source_sha256": "3e25449a44a0e912318db91030eb2e604e0c4eb2f8b5ceaa4ff4f92ae5e5bb80",
    "chapter_id": "BS_C01",
    "section_id": "BS_C01_S02",
    "verse_id": "BS_C01_S02_V23",
    "block_id": "BS_C01_S02_V23_B2",
    "block_type": "bhashya",
    "text": "अन्ये पुन र्मन्यन्ते — नायं भूतयोनेः रूपोपन्यासः , जायमानत्वेनोपन्यासात् । ‘ एतस्माज्जायते प्राणो मनः सर्वेन्द्रियाणि च । खं वायुर्ज्योतिरापः पृथिवी विश्वस्य धारिणी ’ इति हि पूर्वत्र प्राणादि पृथिव्यन्तं तत्त्वजातं जायमानत्वेन निरदिक्षत् । उत्तरत्रापि च ‘ तस्मादग्निः समिधो यस्य सूर्यः ’ इत्येवमादि ‘ अतश्च सर्वा ओषधयो रसश्च ’ इत्येवमन्तं जायमानत्वेनैव निर्देक्ष्यति । इहैव कथमकस्मादन्तराले भूतयोनेः रूपमुपन्यसेत् ? सर्वात्मत्वमपि सृष्टिं परिसमाप्योपदेक्ष्यति — ‘ पुरुष एवेदं विश्वं कर्म ’ (मु. उ. २ । १ । १०) इत्यादिना । श्रुति स्मृत्योश्च त्रैलोक्यशरीरस्य प्रजापतेर्जन्मादि निर्दिश्यमानमुपलभामहे — ‘ हिरण्यगर्भः समवर्तताग्रे भूतस्य जातः पतिरेक आसीत् । स दाधार पृथिवीं द्यामुतेमां कस्मै देवाय हविषा विधेम ’ (ऋ. सं. १० । १२१ । १) इति ; समवर्ततेति अजायतेत्यर्थः — तथा , ‘ स वै शरीरी प्रथमः स वै पुरुष उच्यते । आदिकर्ता स भूतानां ब्रह्माग्रे समवर्तत ’ इति च । विकार पुरुषस्यापि सर्वभूतान्तरात्मत्वं सम्भवति , प्राणात्मना सर्वभूतानामध्यात्ममवस्थानात् । अस्मिन्पक्षे ‘ पुरुष एवेदं विश्वं कर्म ’ इत्यादिसर्वरूपोपन्यासः परमेश्वरप्रतिपत्तिहेतुरिति व्याख्येयम् ॥ २३ ॥",
    "citations": [
      {
        "href": "Mundaka?id=MD_C02_S01_V10",
        "text": "‘ पुरुष"
      },
      {
        "href": "",
        "text": "‘ हिरण्यगर्भः"
      }
    ]
  },
  {
    "source_url": "https://advaitasharada.sringeri.net/display/bhashya/BS/devanagari",
    "source_sha256": "3e25449a44a0e912318db91030eb2e604e0c4eb2f8b5ceaa4ff4f92ae5e5bb80",
    "chapter_id": "BS_C01",
    "section_id": "BS_C01_S02",
    "verse_id": "BS_C01_S02_V23",
    "block_id": "BS_C01_S02_V23_I01",
    "block_type": "leading_bhashya",
    "text": "कुतश्च परमेश्वरो भूतयोनिः ? —",
    "citations": []
  },
  {
    "source_url": "https://advaitasharada.sringeri.net/display/bhashya/BS/devanagari",
    "source_sha256": "3e25449a44a0e912318db91030eb2e604e0c4eb2f8b5ceaa4ff4f92ae5e5bb80",
    "chapter_id": "BS_C01",
    "section_id": "BS_C01_S02",
    "verse_id": "BS_C01_S02_V23",
    "block_id": "BS_C01_S02_V23_VERSETEXT_01",
    "block_type": "versetext",
    "text": "रूपोपन्यासाच्च ॥ २३ ॥",
    "citations": []
  },
  {
    "source_url": "https://advaitasharada.sringeri.net/display/bhashya/BS/devanagari",
    "source_sha256": "3e25449a44a0e912318db91030eb2e604e0c4eb2f8b5ceaa4ff4f92ae5e5bb80",
    "chapter_id": "BS_C01",
    "section_id": "BS_C01_S02",
    "verse_id": "BS_C01_S02_V24",
    "block_id": "BS_C01_S02_V24_B1",
    "block_type": "bhashya",
    "text": "‘ को न आत्मा किं ब्रह्म ’ (छा. उ. ५ । ११ । १) इति ‘ आत्मान मे वेमं वैश्वानरं सम्प्रत्यध्येषि तमेव नो ब्रूहि ’ (छा. उ. ५ । ११ । ६) इति चोपक्रम्य द्युसूर्यवाय्वाकाशवारिपृथिवीनां सुतेजस्त्वादिगुणयोगमेकैकोपासननिन्दया च वैश्वानरं प्रत्येषां मूर्धादिभावमुपदिश्याम्नायते — ‘ यस्त्वेत मे वं प्रादेशमात्रमभिविमानमात्मानं वैश्वानरमुपास्ते , स सर्वेषु लोकेषु सर्वेषु भूतेषु सर्वेष्वात्मस्वन्नमत्ति ;’ (छा. उ. ५ । १८ । १) , ‘ तस्य ह वा एतस्यात्मनो वैश्वानरस्य मूर्धैव सुतेजाश्चक्षुर्विश्वरूपः प्राणः पृथग्वर्त्मात्मा सन्देहो बहुलो वस्तिरेव रयिः पृथिव्येव पादा वुर एव वेदिर्लोमानि बर्हिर्हृदयं गार्हपत्यो मनोऽन्वाहार्यपचन आस्यमाहवनीयः ’ (छा. उ. ५ । १८ । २) इत्यादि । तत्र संशयः — किं वैश्वानरशब्देन जाठरोऽग्निरुपदिश्यते , उत भूताग्निः , अथ तदभिमानिनी देवता , अथवा शारीरः , आहोस्वित्परमेश्वरः इति । किं पुनरत्र संशयकारणम् ? वैश्वानर इति जाठरभूताग्निदेवतानां साधारणशब्दप्रयोगात् , आत्मेति च शारीरपरमेश्वरयोः । तत्र कस्योपादानं न्याय्यं कस्य वा हानमिति भवति संशयः । किं ताव त्प्राप्तम् ? जाठरोऽग्निरिति । कुतः ? तत्र हि विशेषेण क्वचित्प्रयोगो दृश्यते — ‘ अयमग्निर्वैश्वानरो योऽयमन्तः पुरुषे येनेदमन्नं पच्यते यदिदमद्यते ’ (बृ. उ. ५ । ९ । १) इत्यादौ । अग्निमात्रं वा स्यात् , सामान्येनापि प्रयोगदर्शनात् — ‘ विश्वस्मा अग्निं भुवनाय देवा वैश्वानरं केतुमह्नामकृण्वन् ’ (ऋ. सं. १० । ८८ । १२) इत्यादौ । अग्निशरीरा वा देवता स्यात् , तस्यामपि प्रयोगदर्शनात् — ‘ वैश्वानरस्य सुमतौ स्याम राजा हि कं भुवनानामभिश्रीः ’ (ऋ. सं. १ । ९८ । १) इत्येवमाद्यायाः श्रुतेर्देवतायामैश्वर्याद्युपेतायां सम्भवात् । अ था त्मशब्दसामानाधिकरण्यादुपक्रमे च ‘ को न आत्मा किं ब्रह्म ’ इति केवलात्मशब्दप्रयोगादात्मशब्दवशेन वैश्वानरशब्दः परिणेय इत्युच्यते , तथापि शारीर आत्मा स्यात् । तस्य भोक्तृत्वेन वैश्वानरसन्निकर्षात् , प्रादेशमात्रमिति च विशेषणस्य तस्मिन्नुपाधिपरिच्छिन्ने सम्भवात् । तस्मान्नेश्वरो वैश्वानर इत्येवं प्राप्ते ततः",
    "citations": [
      {
        "href": "Chandogya?id=Ch_C05_S11_V01",
        "text": "‘ को"
      },
      {
        "href": "Chandogya?id=Ch_C05_S11_V06",
        "text": "‘ आत्मान"
      },
      {
        "href": "Chandogya?id=Ch_C05_S18_V01",
        "text": "‘ यस्त्वेत"
      },
      {
        "href": "Chandogya?id=Ch_C05_S18_V02",
        "text": "‘ तस्य"
      },
      {
        "href": "Brha?id=BR_C05_S09_V01",
        "text": "‘ अयमग्निर्वैश्वानरो"
      },
      {
        "href": "",
        "text": "‘ विश्वस्मा"
      },
      {
        "href": "",
        "text": "‘ वैश्वानरस्य"
      }
    ]
  },
  {
    "source_url": "https://advaitasharada.sringeri.net/display/bhashya/BS/devanagari",
    "source_sha256": "3e25449a44a0e912318db91030eb2e604e0c4eb2f8b5ceaa4ff4f92ae5e5bb80",
    "chapter_id": "BS_C01",
    "section_id": "BS_C01_S02",
    "verse_id": "BS_C01_S02_V24",
    "block_id": "BS_C01_S02_V24_B2",
    "block_type": "bhashya",
    "text": "इद मुच्यते — वैश्वानरः परमात्मा भवितुमर्हति । कुतः ? साधारणशब्दविशेषात् । साधारणशब्दयोर्विशेषः साधारणशब्दविशेषः । यद्यप्येतावुभावप्यात्मवैश्वानरशब्दौ साधारणशब्दौ — वैश्वानरशब्दस्तु त्रयस्य साधारणः , आत्मशब्दश्च द्वयस्य , तथापि विशेषो दृश्यते , येन परमेश्वरपरत्वं तयोरभ्युपगम्यते — ‘ तस्य ह वा एतस्यात्मनो वैश्वानरस्य मूर्धैव सुतेजाः ’ इत्यादिः । अत्र हि परमेश्वर एव द्युमूर्धत्वादिविशिष्टोऽवस्थान्तरगतः प्रत्यगात्मत्वेनोपन्यस्त आध्यानायेति गम्यते , कारणत्वात् । कारणस्य हि सर्वाभिः कार्यगताभिरवस्थाभिरवस्थावत्त्वात् द्युलोकाद्यवयवत्वमुपपद्यते । ‘ स सर्वेषु लोकेषु सर्वेषु भूतेषु सर्वेष्वात्मस्वन्नमत्ति ’ इति च सर्वलोकाद्याश्रयं फलं श्रूयमाणं परमकारणपरिग्रहे सम्भवति , ‘ एवं हास्य सर्वे पाप्मानः प्रदूयन्ते ’ (छा. उ. ५ । २४ । ३) इति च तद्विदः सर्वपाप्मप्रदाहश्रवणम् , ‘ को न आत्मा किं ब्रह्म ’ इति चात्मब्रह्मशब्दाभ्यामुपक्रमः ; — इत्येवमेतानि लिङ्गानि परमेश्वरमेव गमयन्ति । तस्मात्परमेश्वर एव वैश्वानरः ॥ २४ ॥",
    "citations": [
      {
        "href": "Chandogya?id=Ch_C05_S24_V03",
        "text": "‘ एवं"
      }
    ]
  },
  {
    "source_url": "https://advaitasharada.sringeri.net/display/bhashya/BS/devanagari",
    "source_sha256": "3e25449a44a0e912318db91030eb2e604e0c4eb2f8b5ceaa4ff4f92ae5e5bb80",
    "chapter_id": "BS_C01",
    "section_id": "BS_C01_S02",
    "verse_id": "BS_C01_S02_V24",
    "block_id": "BS_C01_S02_V24_VERSETEXT_01",
    "block_type": "versetext",
    "text": "वैश्वानरः साधारणशब्दविशेषात् ॥ २४ ॥",
    "citations": []
  },
  {
    "source_url": "https://advaitasharada.sringeri.net/display/bhashya/BS/devanagari",
    "source_sha256": "3e25449a44a0e912318db91030eb2e604e0c4eb2f8b5ceaa4ff4f92ae5e5bb80",
    "chapter_id": "BS_C01",
    "section_id": "BS_C01_S02",
    "verse_id": "BS_C01_S02_V25",
    "block_id": "BS_C01_S02_V25_B1",
    "block_type": "bhashya",
    "text": "इतश्च परमेश्वर एव वैश्वानरः ; यस्मात्परमेश्वरस्यैव ‘ अग्निरास्यं द्यौर्मूर्धा ’ इतीदृशं त्रैलोक्यात्मकं रूपं स्मर्यते — ‘ यस्याग्निरास्यं द्यौर्मूर्धा खं नाभिश्चरणौ क्षितिः । सूर्यश्चक्षुर्दिशः श्रोत्रं तस्मै लोकात्मने नमः ’ इति । एतत्स्मर्यमाणं रूपं मूलभूतां श्रुतिमनुमापयदस्य वैश्वानरशब्दस्य परमेश्वरपरत्वे अनुमानं लिङ्गं गमकं स्यादित्यर्थः । इतिशब्दो हेत्वर्थे — यस्मादिदं गमकम् , तस्मादपि वैश्वानरः परमात्मैवेत्यर्थः । यद्यपि स्तुति रि यम् — ‘ तस्मै लोकात्मने नमः ’ इति , तथापि स्तुतित्वमपि नासति मूलभूते वेदवाक्ये सम्यक् ईदृशेन रूपेण सम्भवति । ‘ द्यां मूर्धानं यस्य विप्रा वदन्ति खं वै नाभिं चन्द्रसूर्यौ च नेत्रे । दिशः श्रोत्रे विद्धि पादौ क्षितिं च सोऽचिन्त्यात्मा सर्वभूतप्रणेता ’ इत्येवंजातीयका च स्मृतिरिहोदाहर्तव्या ॥ २५ ॥",
    "citations": []
  },
  {
    "source_url": "https://advaitasharada.sringeri.net/display/bhashya/BS/devanagari",
    "source_sha256": "3e25449a44a0e912318db91030eb2e604e0c4eb2f8b5ceaa4ff4f92ae5e5bb80",
    "chapter_id": "BS_C01",
    "section_id": "BS_C01_S02",
    "verse_id": "BS_C01_S02_V25",
    "block_id": "BS_C01_S02_V25_VERSETEXT_01",
    "block_type": "versetext",
    "text": "स्मर्यमाणमनुमानं स्यादिति ॥ २५ ॥",
    "citations": []
  },
  {
    "source_url": "https://advaitasharada.sringeri.net/display/bhashya/BS/devanagari",
    "source_sha256": "3e25449a44a0e912318db91030eb2e604e0c4eb2f8b5ceaa4ff4f92ae5e5bb80",
    "chapter_id": "BS_C01",
    "section_id": "BS_C01_S02",
    "verse_id": "BS_C01_S02_V26",
    "block_id": "BS_C01_S02_V26_B1",
    "block_type": "bhashya",
    "text": "अत्राह — न परमेश्वरो वैश्वानरो भवितुमर्हति । कुतः ? शब्दादिभ्योऽन्तःप्रतिष्ठानाच्च । शब्दस्तावत् — वैश्वानरशब्दो न परमेश्वरे सम्भवति , अर्थान्तरे रूढत्वात् । तथाग्निशब्दः ‘ स एषोऽग्निर्वैश्वानरः ’ इति । आदिशब्दात् ‘ हृदयं गार्हपत्यः ’ (छा. उ. ५ । १८ । २) इत्याद्यग्नित्रेताप्रकल्पनम् ; ‘ तद्यद्भक्तं प्रथममागच्छेत्तद्धोमीयम् ’ (छा. उ. ५ । १९ । १) इत्यादिना च प्राणाहुत्यधिकरणतासङ्कीर्तनम् । एतेभ्यो हेतुभ्यो जाठरो वैश्वानरः प्रत्येतव्यः । त था न्तःप्रतिष्ठानमपि श्रूयते — ‘ पुरुषेऽन्तः प्रतिष्ठितं वेद ’ इति । तच्च जाठरे सम्भवति । यदप्युक्तम् ‘ मूर्धैव सुतेजाः ’ इत्यादेर्विशेषात्कारणात्परमात्मा वैश्वानर इति , अत्र ब्रूमः — कुतो ह्येष निर्णयः , यदुभयथापि विशेषप्रतिभाने सति परमेश्वरविषय एव विशेष आश्रयणीयो न जाठरविषय इति । अथवा भूताग्नेरन्तर्बहिश्चावतिष्ठमानस्यैष निर्देशो भविष्यति । तस्यापि हि द्युलोकादिसम्बन्धो मन्त्रवर्णा दवगम्यते — ‘ यो भानुना पृथिवीं द्यामुतेमामाततान रोदसी अन्तरिक्षम् ’ (ऋ. सं. १० । ८८ । ४) इत्यादौ । अथवा तच्छरीराया देवताया ऐश्वर्ययोगात् द्युलोकाद्यवयवत्वं भविष्यति । तस्मान्न परमेश्वरो वैश्वानर इति ॥",
    "citations": [
      {
        "href": "Chandogya?id=Ch_C05_S18_V02",
        "text": "‘ हृदयं"
      },
      {
        "href": "Chandogya?id=Ch_C05_S19_V01",
        "text": "‘ तद्यद्भक्तं"
      },
      {
        "href": "",
        "text": "‘ यो"
      }
    ]
  },
  {
    "source_url": "https://advaitasharada.sringeri.net/display/bhashya/BS/devanagari",
    "source_sha256": "3e25449a44a0e912318db91030eb2e604e0c4eb2f8b5ceaa4ff4f92ae5e5bb80",
    "chapter_id": "BS_C01",
    "section_id": "BS_C01_S02",
    "verse_id": "BS_C01_S02_V26",
    "block_id": "BS_C01_S02_V26_B2",
    "block_type": "bhashya",
    "text": "अत्रोच्यते — न तथादृष्ट्युपदेशादिति । न शब्दादिभ्यः कारणेभ्यः परमेश्वरस्य प्रत्याख्यानं युक्तम् । कुतः ? तथा जाठरापरित्यागेन , दृष्ट्युपदेशात् । परमेश्वरदृष्टिर्हि जाठरे वैश्वानरे इहोपदिश्यते — ‘ मनो ब्रह्मेत्युपासीत ’ (छा. उ. ३ । १८ । १) इत्यादिवत् । अथवा जाठर वैश्वानरोपाधिः परमेश्वर इह द्रष्टव्यत्वेनोपदिश्यते — ‘ मनोमयः प्राणशरीरो भारूपः ’ (छा. उ. ३ । १४ । २) इत्यादिवत् । यदि चे ह परमेश्वरो न विवक्ष्येत , केवल एव जाठरोऽग्निर्विवक्ष्येत , ततः ‘ मूर्धैव सुतेजाः ’ इत्यादेर्विशेषस्यासम्भव एव स्यात् । यथा तु देवताभूताग्निव्यपाश्रयेणाप्ययं विशेष उपपादयितुं न शक्यते , तथोत्तरसूत्रे वक्ष्यामः । यदि च केवल एव जाठरो विवक्ष्येत , पुरुषेऽन्तःप्रतिष्ठितत्वं केवलं तस्य स्यात् । न तु पुरुषत्वम् । पुरुषमपि चैनमधीयते वाजसनेयिनः — ‘ स एषोऽग्निर्वैश्वानरो यत्पुरुषः स यो हैतमेवमग्निं वैश्वानरं पुरुषं पुरुषेऽन्तः प्रतिष्ठितं वेद ’ (श. ब्रा. १० । ६ । १ । ११) इति । परमेश्वरस्य तु सर्वात्मत्वात्पुरुषत्वं पुरुषेऽन्तःप्रतिष्ठितत्वं चोभयमुपपद्यते । ये तु ‘ पुरुषविधमपि चैनमधीयते ’ इति सूत्रावयवं पठन्ति , तेषामेषोऽर्थः — केवलजाठरपरिग्रहे पुरुषेऽन्तःप्रतिष्ठितत्वं केवलं स्यात् । न तु पुरुषविधत्वम् । पुरुषविधमपि चैनमधीयते वाजसनेयिनः — ‘ पुरुषविधं पुरुषेऽन्तः प्रतिष्ठितं वेद ’ इति । पुरुषविधत्वं च प्रकरणात् यदधिदैवतं द्युमूर्धत्वादि पृथिवीप्रतिष्ठितत्वान्तम् , यच्चाध्यात्मं प्रसिद्धं मूर्धत्वादि चुबुकप्रतिष्ठितत्वान्तम् , तत्परिगृह्यते ॥ २६ ॥",
    "citations": [
      {
        "href": "Chandogya?id=Ch_C03_S18_V01",
        "text": "‘ मनो"
      },
      {
        "href": "Chandogya?id=Ch_C03_S14_V02",
        "text": "‘ मनोमयः"
      },
      {
        "href": "",
        "text": "‘ स"
      }
    ]
  },
  {
    "source_url": "https://advaitasharada.sringeri.net/display/bhashya/BS/devanagari",
    "source_sha256": "3e25449a44a0e912318db91030eb2e604e0c4eb2f8b5ceaa4ff4f92ae5e5bb80",
    "chapter_id": "BS_C01",
    "section_id": "BS_C01_S02",
    "verse_id": "BS_C01_S02_V26",
    "block_id": "BS_C01_S02_V26_VERSETEXT_01",
    "block_type": "versetext",
    "text": "शब्दादिभ्योऽन्तःप्रतिष्ठानाच्च नेति चेन्न तथादृष्ट्युपदेशादसम्भवात्पुरुषमपि चैनमधीयते ॥ २६॥",
    "citations": []
  },
  {
    "source_url": "https://advaitasharada.sringeri.net/display/bhashya/BS/devanagari",
    "source_sha256": "3e25449a44a0e912318db91030eb2e604e0c4eb2f8b5ceaa4ff4f92ae5e5bb80",
    "chapter_id": "BS_C01",
    "section_id": "BS_C01_S02",
    "verse_id": "BS_C01_S02_V27",
    "block_id": "BS_C01_S02_V27_B1",
    "block_type": "bhashya",
    "text": "यत्पुन रु क्तम् — भूताग्नेरपि मन्त्रवर्णे द्युलोकादिसम्बन्धदर्शनात् ‘ मूर्धैव सुतेजाः ’ इत्याद्यवयवकल्पनं तस्यैव भविष्यतीति , तच्छरीराया देवताया वा ऐश्वर्ययोगादिति ; तत्परिहर्तव्यम् । अत्रोच्यते — अत एवोक्तेभ्यो हेतुभ्यो न देवता वैश्वानरः । तथा भूताग्निरपि न वैश्वानरः । न हि भूताग्ने रौष्ण्यप्रकाशमात्रात्मकस्य द्युमूर्धत्वादिकल्पनोपपद्यते , विकारस्य विकारान्तरात्मत्वासम्भवात् । तथा देवतायाः सत्यप्यैश्वर्ययोगे न द्युमूर्धत्वादिकल्पना सम्भवति , अकारणत्वात् परमेश्वराधीनैश्वर्यत्वाच्च । आत्मशब्दासम्भवश्च सर्वेष्वेषु पक्षेषु स्थित एव ॥ २७ ॥",
    "citations": []
  },
  {
    "source_url": "https://advaitasharada.sringeri.net/display/bhashya/BS/devanagari",
    "source_sha256": "3e25449a44a0e912318db91030eb2e604e0c4eb2f8b5ceaa4ff4f92ae5e5bb80",
    "chapter_id": "BS_C01",
    "section_id": "BS_C01_S02",
    "verse_id": "BS_C01_S02_V27",
    "block_id": "BS_C01_S02_V27_VERSETEXT_01",
    "block_type": "versetext",
    "text": "अत एव न देवता भूतं च ॥ २७ ॥",
    "citations": []
  },
  {
    "source_url": "https://advaitasharada.sringeri.net/display/bhashya/BS/devanagari",
    "source_sha256": "3e25449a44a0e912318db91030eb2e604e0c4eb2f8b5ceaa4ff4f92ae5e5bb80",
    "chapter_id": "BS_C01",
    "section_id": "BS_C01_S02",
    "verse_id": "BS_C01_S02_V28",
    "block_id": "BS_C01_S02_V28_B1",
    "block_type": "bhashya",
    "text": "पूर्वं जाठराग्निप्रतीको जाठराग्न्युपाधिको वा परमेश्वर उपास्य इत्युक्तम् अन्तःप्रतिष्ठितत्वाद्यनुरोधेन । इदानीं तु विनैव प्रतीकोपाधिकल्पनाभ्यां साक्षादपि परमेश्वरोपासनपरिग्रहे न कश्चिद्विरोध इति जैमिनिराचार्यो मन्यते । ननु जाठराग्न्यपरिग्रहेऽन्तःप्रतिष्ठितत्ववचनं शब्दादीनि च कारणानि विरुध्येरन्निति । अत्रोच्यते — अन्तःप्रतिष्ठितत्ववचनं तावन्न विरुध्यते । न हीह ‘ पुरुषविधं पुरुषेऽन्तः प्रतिष्ठितं वेद ’ इति जाठराग्न्यभिप्रायेणेदमुच्यते , तस्याप्रकृतत्वादसंशब्दितत्वाच्च । कथं तर्हि ? यत्प्रकृतं मूर्धादिचुबुकान्तेषु पुरुषावयवेषु पुरुषविधत्वं कल्पितम् , तदभिप्रायेणेदमुच्यते — ‘ पुरुषविधं पुरुषेऽन्तः प्रतिष्ठितं वेद ’ इति । यथा वृक्षे शाखां प्रतिष्ठितां पश्यतीति , तद्वत् । अथवा यः प्रकृतः परमात्मा अध्यात्ममधिदैवतं च पुरुषविधत्वोपाधिः , तस्य यत्केवलं साक्षिरूपम् , तदभिप्रायेणेदमुच्यते — ‘ पुरुषविधं पुरुषेऽन्तः प्रतिष्ठितं वेद ’ इति । निश्चिते च पूर्वापरालोचनवशेन परमात्मपरिग्रहे , तद्विषय एव वैश्वानरशब्दः केनचिद्योगेन वर्तिष्यते — विश्वश्चायं नरश्चेति , विश्वेषां वायं नरः , विश्वे वा नरा अस्येति विश्वानरः परमात्मा , सर्वात्मत्वात् , विश्वानर एव वैश्वानरः । तद्धितोऽनन्यार्थः , राक्षसवायसादिवत् । अग्निशब्दोऽप्यग्रणीत्वादियोगाश्रयणेन परमात्मविषय एव भविष्यति । गार्हप त्या दिकल्पनं प्राणाहुत्यधिकरणत्वं च परमात्मनोऽपि सर्वात्मत्वादुपपद्यते ॥ २८ ॥",
    "citations": []
  },
  {
    "source_url": "https://advaitasharada.sringeri.net/display/bhashya/BS/devanagari",
    "source_sha256": "3e25449a44a0e912318db91030eb2e604e0c4eb2f8b5ceaa4ff4f92ae5e5bb80",
    "chapter_id": "BS_C01",
    "section_id": "BS_C01_S02",
    "verse_id": "BS_C01_S02_V28",
    "block_id": "BS_C01_S02_V28_VERSETEXT_01",
    "block_type": "versetext",
    "text": "साक्षादप्यविरोधं जैमिनिः ॥ २८ ॥",
    "citations": []
  },
  {
    "source_url": "https://advaitasharada.sringeri.net/display/bhashya/BS/devanagari",
    "source_sha256": "3e25449a44a0e912318db91030eb2e604e0c4eb2f8b5ceaa4ff4f92ae5e5bb80",
    "chapter_id": "BS_C01",
    "section_id": "BS_C01_S02",
    "verse_id": "BS_C01_S02_V29",
    "block_id": "BS_C01_S02_V29_B1",
    "block_type": "bhashya",
    "text": "अतिमात्रस्यापि परमेश्वरस्य प्रादेशमात्रत्वमभिव्यक्तिनिमित्तं स्यात् । अभिव्यज्यते किल प्रादेशमात्रपरिमाणः परमेश्वर उपासकानां कृते । प्रदेशविशेषेषु वा हृदयादिषूपलब्धिस्थानेषु विशेषेणाभिव्यज्यते । अतः परमेश्वरेऽपि प्रादेशमात्रश्रुतिरभिव्यक्तेरुपपद्यत इत्याश्मरथ्य आचार्यो मन्यते ॥ २९ ॥",
    "citations": []
  },
  {
    "source_url": "https://advaitasharada.sringeri.net/display/bhashya/BS/devanagari",
    "source_sha256": "3e25449a44a0e912318db91030eb2e604e0c4eb2f8b5ceaa4ff4f92ae5e5bb80",
    "chapter_id": "BS_C01",
    "section_id": "BS_C01_S02",
    "verse_id": "BS_C01_S02_V29",
    "block_id": "BS_C01_S02_V29_I01",
    "block_type": "leading_bhashya",
    "text": "कथं पुनः परमेश्वरपरिग्रहे प्रादेशमात्रश्रुतिरुपपद्यत इति , तां व्याख्यातु मारभते —",
    "citations": []
  },
  {
    "source_url": "https://advaitasharada.sringeri.net/display/bhashya/BS/devanagari",
    "source_sha256": "3e25449a44a0e912318db91030eb2e604e0c4eb2f8b5ceaa4ff4f92ae5e5bb80",
    "chapter_id": "BS_C01",
    "section_id": "BS_C01_S02",
    "verse_id": "BS_C01_S02_V29",
    "block_id": "BS_C01_S02_V29_VERSETEXT_01",
    "block_type": "versetext",
    "text": "अभिव्यक्तेरित्याश्मरथ्यः ॥ २९ ॥",
    "citations": []
  },
  {
    "source_url": "https://advaitasharada.sringeri.net/display/bhashya/BS/devanagari",
    "source_sha256": "3e25449a44a0e912318db91030eb2e604e0c4eb2f8b5ceaa4ff4f92ae5e5bb80",
    "chapter_id": "BS_C01",
    "section_id": "BS_C01_S02",
    "verse_id": "BS_C01_S02_V30",
    "block_id": "BS_C01_S02_V30_B1",
    "block_type": "bhashya",
    "text": "प्रादेशमात्रहृदयप्रतिष्ठेन वायं मनसानुस्मर्यते । तेन ‘ प्रादेशमात्रः ’ इत्युच्यते । यथा प्रस्थमिता यवाः प्रस्था इत्युच्यन्ते , तद्वत् । यद्यपि च यवेषु स्वगतमेव परिमाणं प्रस्थसम्बन्धाद्व्यज्यते , न चेह परमेश्वरगतं किञ्चित्परिमाणमस्ति , यद्धृदयसम्बन्धाद्व्यज्येत ; तथापि प्रयुक्तायाः प्रादेशमात्रश्रुतेः सम्भवति यथाकथञ्चि द नुस्मरणमालम्बनमित्युच्यते । प्रादेश मात्रत्वेन वायमप्रादेशमात्रोऽप्यनुस्मरणीयः प्रादेशमात्रश्रुत्यर्थवत्तायै । एवमनुस्मृतिनिमित्ता परमेश्वरे प्रादेशमात्रश्रुतिरिति बादरिराचार्यो मन्यते ॥ ३० ॥",
    "citations": []
  },
  {
    "source_url": "https://advaitasharada.sringeri.net/display/bhashya/BS/devanagari",
    "source_sha256": "3e25449a44a0e912318db91030eb2e604e0c4eb2f8b5ceaa4ff4f92ae5e5bb80",
    "chapter_id": "BS_C01",
    "section_id": "BS_C01_S02",
    "verse_id": "BS_C01_S02_V30",
    "block_id": "BS_C01_S02_V30_VERSETEXT_01",
    "block_type": "versetext",
    "text": "अनुस्मृतेर्बादरिः ॥ ३० ॥",
    "citations": []
  },
  {
    "source_url": "https://advaitasharada.sringeri.net/display/bhashya/BS/devanagari",
    "source_sha256": "3e25449a44a0e912318db91030eb2e604e0c4eb2f8b5ceaa4ff4f92ae5e5bb80",
    "chapter_id": "BS_C01",
    "section_id": "BS_C01_S02",
    "verse_id": "BS_C01_S02_V31",
    "block_id": "BS_C01_S02_V31_B1",
    "block_type": "bhashya",
    "text": "सम्पत्तिनिमित्ता वा स्यात्प्रादेशमात्रश्रुतिः । कुतः ? तथाहि समानप्रकरणं वाजसनेयिब्राह्मणं द्युप्रभृतीन्पृथिवीपर्यन्तांस्त्रैलोक्यात्मनो वैश्वानरस्यावयवानध्यात्ममूर्धप्रभृतिषु चुबुकपर्यन्तेषु देहावयवेषु सम्पादयत्प्रादेशमात्रसम्पत्तिं परमेश्वरस्य दर्शयति — ‘ प्रादेशमात्रमिव ह वै देवाः सुविदिता अभिसम्पन्नास्तथा नु व एतान्वक्ष्यामि यथा प्रादेशमात्रमेवाभिसम्पादयिष्यामीति । स होवाच मूर्धानमुपदिशन्नुवाचैष वा अतिष्ठा वैश्वानर इति । चक्षुषी उपदिशन्नुवाचैष वै सुतेजा वैश्वानर इति । नासिके उपदिशन्नुवाचैष वै पृथग्वर्त्मात्मा वैश्वानर इति । मुख्यमाकाशमुपदिशन्नुवाचैष वै बहुलो वैश्वानर इति । मुख्या अप उपदिशन्नुवाचैष वै रयिर्वैश्वानर इति । चुबुकमुपदिशन्नुवाचैष वै प्रतिष्ठा वैश्वानरः ’ इति । चुबुकमित्यधरं मुखफलकमुच्यते । यद्यपि वाजसनेयके द्यौरतिष्ठात्वगुणा समाम्नायते , आदित्यश्च सुतेजस्त्वगुणः , छान्दोग्ये पुनः द्यौः सुतेजस्त्वगुणा समाम्नायते , आदित्यश्च विश्वरूपत्वगुणः ; तथापि नैतावता विशेषेण किञ्चिद्धीयते , प्रादेशमात्रश्रुतेरविशेषात् , सर्वशाखाप्रत्ययत्वाच्च । सम्पत्तिनिमित्तां प्रादेशमात्रश्रुतिं युक्ततरां जैमिनिराचार्यो मन्यते ॥ ३१ ॥",
    "citations": []
  },
  {
    "source_url": "https://advaitasharada.sringeri.net/display/bhashya/BS/devanagari",
    "source_sha256": "3e25449a44a0e912318db91030eb2e604e0c4eb2f8b5ceaa4ff4f92ae5e5bb80",
    "chapter_id": "BS_C01",
    "section_id": "BS_C01_S02",
    "verse_id": "BS_C01_S02_V31",
    "block_id": "BS_C01_S02_V31_VERSETEXT_01",
    "block_type": "versetext",
    "text": "सम्पत्तेरिति जैमिनिस्तथा हि दर्शयति ॥ ३१ ॥",
    "citations": []
  },
  {
    "source_url": "https://advaitasharada.sringeri.net/display/bhashya/BS/devanagari",
    "source_sha256": "3e25449a44a0e912318db91030eb2e604e0c4eb2f8b5ceaa4ff4f92ae5e5bb80",
    "chapter_id": "BS_C01",
    "section_id": "BS_C01_S02",
    "verse_id": "BS_C01_S02_V32",
    "block_id": "BS_C01_S02_V32_B1",
    "block_type": "bhashya",
    "text": "आमनन्ति चैनं परमेश्वरमस्मिन्मूर्धचुबुकान्तराले जाबालाः — ‘ य एषोऽनन्तोऽव्यक्त आत्मा सोऽविमुक्ते प्रतिष्ठित इति । सोऽविमुक्तः कस्मिन्प्रतिष्ठित इति । वरणायां नास्यां च मध्ये प्रतिष्ठित इति । का वै वरणा का च नासीति ’ । तत्र चेमामेव नासिकाम् ‘ सर्वाणीन्द्रियकृतानि पापानि वारयतीति सा वरणा , सर्वाणीन्द्रियकृतानि पापानि नाशयतीति सा नासी ’ इति वरणानासीति निरुच्य , पुनरप्यामनन्ति — ‘ कतमच्चास्य स्थानं भवतीति । भ्रुवोर्घ्राणस्य च यः सन्धिः स एष द्युलोकस्य परस्य च सन्धिर्भवति ’ (जा. उ. २) इति । तस्मादुपपन्ना परमेश्वरे प्रादेशमात्रश्रुतिः । अभिविमानश्रुतिः प्रत्यगात्मत्वाभिप्राया । प्रत्यगात्मतया सर्वैः प्राणिभिरभिविमीयत इत्यभिविमानः । अभिगतो वायं प्रत्यगात्मत्वात् , विमानश्च मानवियोगात् इत्यभिविमानः । अभिविमिमीते वा सर्वं जगत् , कारणत्वादित्यभिविमानः । तस्मात्परमेश्वरो वैश्वानर इति सिद्धम् ॥ ३२ ॥",
    "citations": [
      {
        "href": "jbl?id=JB_V02",
        "text": "‘ कतमच्चास्य"
      }
    ]
  },
  {
    "source_url": "https://advaitasharada.sringeri.net/display/bhashya/BS/devanagari",
    "source_sha256": "3e25449a44a0e912318db91030eb2e604e0c4eb2f8b5ceaa4ff4f92ae5e5bb80",
    "chapter_id": "BS_C01",
    "section_id": "BS_C01_S02",
    "verse_id": "BS_C01_S02_V32",
    "block_id": "BS_C01_S02_V32_VERSETEXT_01",
    "block_type": "versetext",
    "text": "आमनन्ति चैनमस्मिन् ॥ ३२ ॥",
    "citations": []
  }
]
