[
  {
    "text_name": "Taitiriya",
    "source_url": "https://advaitasharada.sringeri.net/display/bhashya",
    "source_sha256": "d0376df75bd25f383f2c79d9c21cbed7d2121a1245773d62c74999eb51bb65de",
    "text_id": "T",
    "chapter_id": "T_C01",
    "section_id": "T_C01_S09",
    "verse_id": "T_C01_S09_V01",
    "block_id": "T_C01_S09_V01_B01",
    "block_type": "bhashya",
    "record_kind": "bhasya",
    "source_block_class": "bhashya",
    "text": "ऋतमिति व्याख्यातम् । स्वाध्यायः अध्ययनम् । प्रवचनमध्यापनं ब्रह्मयज्ञो वा । एतानि ऋतादीनि, अनुष्ठेयानि इति वाक्यशेषः । सत्यं सत्यवचनं यथाव्याख्यातार्थं वा । तपः कृच्छ्रादि । दमः बाह्यकरणोपशमः । शमः अन्तःकरणोपशमः । अग्नयश्च आधातव्याः । अग्निहोत्रं च होतव्यम् । अतिथयश्च पूज्याः । मानुषमिति लौकिकः संव्यवहारः । तच्च यथाप्राप्तमनुष्ठेयम् । प्रजा च उत्पाद्या । प्रजनश्च प्रजननम् ; ऋतौ भार्यागमनमित्यर्थः । प्रजातिः पौत्रोत्पत्तिः ; पुत्रो निवेशयितव्य इत्येतत् । सर्वैरेतैः कर्मभिर्युक्तस्यापि स्वाध्यायप्रवचने यत्नतोऽनुष्ठेये इत्येवमर्थं सर्वेण सह स्वाध्यायप्रवचनग्रहणम् । स्वाध्यायाधीनं ह्यर्थज्ञानम् । अर्थज्ञानाधीनं च परं श्रेयः । प्रवचनं च तदविस्मरणार्थं धर्मवृद्ध्यर्थं च । ततः स्वाध्यायप्रवचनयोरादरः कार्यः । सत्यमिति सत्यमेवानुष्ठेयमिति सत्यवचाः सत्यमेव वचो यस्य सोऽयं सत्यवचाः, नाम वा तस्य ; राथीतरः रथीतरसगोत्रः राथीतर आचार्यो मन्यते । तप इति तप एव कर्तव्यमिति तपोनित्यः तपसि नित्यः तपःपरः, तपोनित्य इति वा नाम ; पौरुशिष्टिः पुरुशिष्टस्यापत्यं पौरुशिष्टिराचार्यो मन्यते । स्वाध्यायप्रवचने एव अनुष्ठेये इति नाको नामतः मुद्गलस्यापत्यं मौद्गल्य आचार्यो मन्यते । तद्धि तपस्तद्धि तपः । यस्मात्स्वाध्यायप्रवचने एव तपः, तस्मात्ते एवानुष्ठेये इति । उक्तानामपि सत्यतपःस्वाध्यायप्रवचनानां पुनर्ग्रहणमादरार्थम् ॥",
    "citations": []
  },
  {
    "text_name": "Taitiriya",
    "source_url": "https://advaitasharada.sringeri.net/display/bhashya",
    "source_sha256": "d0376df75bd25f383f2c79d9c21cbed7d2121a1245773d62c74999eb51bb65de",
    "text_id": "T",
    "chapter_id": "T_C01",
    "section_id": "T_C01_S09",
    "verse_id": "T_C01_S09_V01",
    "block_id": "T_C01_S09_V01_I01",
    "block_type": "leading_bhashya",
    "record_kind": "bhasya",
    "source_block_class": "leading_bhashya",
    "text": "विज्ञानादेवाप्नोति स्वाराज्यमित्युक्तत्वात् श्रौतस्मार्तानां कर्मणामानर्थक्यं प्राप्तमित्येतन्मा प्रापदिति कर्मणां पुरुषार्थं प्रति साधनत्वप्रदर्शनार्थ इहोपन्यासः -",
    "citations": []
  },
  {
    "text_name": "Taitiriya",
    "source_url": "https://advaitasharada.sringeri.net/display/bhashya",
    "source_sha256": "d0376df75bd25f383f2c79d9c21cbed7d2121a1245773d62c74999eb51bb65de",
    "text_id": "T",
    "chapter_id": "T_C01",
    "section_id": "T_C01_S09",
    "verse_id": "T_C01_S09_V01",
    "block_id": "T_C01_S09_V01_VERSETEXT_01",
    "block_type": "versetext",
    "record_kind": "sutra",
    "source_block_class": "versetext",
    "text": "ऋतं च स्वाध्यायप्रवचने च । सत्यं च स्वाध्यायप्रवचने च । तपश्च स्वाध्यायप्रवचने च । दमश्च स्वाध्यायप्रवचने च । शमश्च स्वाध्यायप्रवचने च । अग्नयश्य स्वाध्यायप्रवचने च । अग्निहोत्रं च स्वाध्यायप्रवचने च । अतिथयश्च स्वाध्यायप्रवचने च । मानुषं च स्वाध्यायप्रवचने च । प्रजा च स्वाध्यायप्रवचने च । प्रजनश्च स्वाध्यायप्रवचने च । प्रजातिश्च स्वाध्यायप्रवचने च । सत्यमिति सत्यवचा राथीतरः । तप इति तपोनित्यः पौरुशिष्टिः । स्वाध्यायप्रवचने एवेति नाको मौद्गल्यः । तद्धि तपस्तद्धि तपः ॥ १ ॥",
    "citations": []
  }
]
