[
  {
    "text_name": "Chandogya",
    "source_url": "https://advaitasharada.sringeri.net/display/bhashya",
    "source_sha256": "6f622df9fb9d6cc6d7d8d2f70b063b04fb4053cf1c1822042b989578a63d96b2",
    "text_id": "Ch",
    "chapter_id": "Ch_C07",
    "section_id": "Ch_C07_S21",
    "verse_id": "Ch_C07_S21_V01",
    "block_id": "Ch_C07_S21_V01_B01",
    "block_type": "bhashya",
    "text": "यदा वै करोति । कृतिः इन्द्रियसंयमः चित्तैकाग्रताकरणं च । सत्यां हि तस्यां निष्ठादीनि यथोक्तानि भवन्ति विज्ञानावसानानि ॥",
    "citations": []
  },
  {
    "text_name": "Chandogya",
    "source_url": "https://advaitasharada.sringeri.net/display/bhashya",
    "source_sha256": "6f622df9fb9d6cc6d7d8d2f70b063b04fb4053cf1c1822042b989578a63d96b2",
    "text_id": "Ch",
    "chapter_id": "Ch_C07",
    "section_id": "Ch_C07_S21",
    "verse_id": "Ch_C07_S21_V01",
    "block_id": "Ch_C07_S21_V01_VERSETEXT_01",
    "block_type": "versetext",
    "text": "यदा वै करोत्यथ निस्तिष्ठति नाकृत्वा निस्तिष्ठति कृत्वैव निस्तिष्ठति कृतिस्त्वेव विजिज्ञासितव्येति कृतिं भगवो विजिज्ञास इति ॥ १ ॥",
    "citations": []
  }
]
